{
  "bestSolution": {
    "revenue": 1056052
  },
  "checkPoints": [
    {
      "objective": 953327.0,
      "time": 0.9709999561309814
    },
    {
      "objective": 1019780.0,
      "time": 0.9909999370574951
    },
    {
      "objective": 1024045.0,
      "time": 1.4110000133514404
    },
    {
      "objective": 1030051.0,
      "time": 1.4779999256134033
    },
    {
      "objective": 1030192.0,
      "time": 1.7999999523162842
    },
    {
      "objective": 1032413.0,
      "time": 2.11299991607666
    },
    {
      "objective": 1032526.0,
      "time": 2.634999990463257
    },
    {
      "objective": 1034935.0,
      "time": 2.6610000133514404
    },
    {
      "objective": 1035388.0,
      "time": 2.9830000400543213
    },
    {
      "objective": 1035749.0,
      "time": 3.121000051498413
    },
    {
      "objective": 1035922.0,
      "time": 3.1530001163482666
    },
    {
      "objective": 1036841.0,
      "time": 3.4170000553131104
    },
    {
      "objective": 1036860.0,
      "time": 3.4570000171661377
    },
    {
      "objective": 1037358.0,
      "time": 3.486999988555908
    },
    {
      "objective": 1037360.0,
      "time": 4.003000020980835
    },
    {
      "objective": 1037663.0,
      "time": 4.367000102996826
    },
    {
      "objective": 1038121.0,
      "time": 4.546999931335449
    },
    {
      "objective": 1038333.0,
      "time": 4.7209999561309814
    },
    {
      "objective": 1039701.0,
      "time": 4.91100001335144
    },
    {
      "objective": 1040424.0,
      "time": 5.267999887466431
    },
    {
      "objective": 1040458.0,
      "time": 5.54800009727478
    },
    {
      "objective": 1040572.0,
      "time": 6.757999897003174
    },
    {
      "objective": 1040597.0,
      "time": 6.940999984741211
    },
    {
      "objective": 1040874.0,
      "time": 7.171000003814697
    },
    {
      "objective": 1040883.0,
      "time": 8.430000066757202
    },
    {
      "objective": 1040994.0,
      "time": 8.716000080108643
    },
    {
      "objective": 1041026.0,
      "time": 9.270999908447266
    },
    {
      "objective": 1041498.0,
      "time": 10.131999969482422
    },
    {
      "objective": 1041524.0,
      "time": 10.450000047683716
    },
    {
      "objective": 1042109.0,
      "time": 10.581000089645386
    },
    {
      "objective": 1042178.0,
      "time": 10.92799997329712
    },
    {
      "objective": 1042374.0,
      "time": 11.96399998664856
    },
    {
      "objective": 1042427.0,
      "time": 12.187000036239624
    },
    {
      "objective": 1042672.0,
      "time": 12.45799994468689
    },
    {
      "objective": 1042715.0,
      "time": 13.358000040054321
    },
    {
      "objective": 1044160.0,
      "time": 13.562999963760376
    },
    {
      "objective": 1044538.0,
      "time": 13.744999885559082
    },
    {
      "objective": 1044797.0,
      "time": 14.125999927520752
    },
    {
      "objective": 1044951.0,
      "time": 14.542999982833862
    },
    {
      "objective": 1045152.0,
      "time": 14.911999940872192
    },
    {
      "objective": 1045202.0,
      "time": 15.14299988746643
    },
    {
      "objective": 1045866.0,
      "time": 16.283999919891357
    },
    {
      "objective": 1045906.0,
      "time": 17.30299997329712
    },
    {
      "objective": 1046019.0,
      "time": 18.117000102996826
    },
    {
      "objective": 1046288.0,
      "time": 18.13100004196167
    },
    {
      "objective": 1046554.0,
      "time": 19.276999950408936
    },
    {
      "objective": 1046656.0,
      "time": 19.91100001335144
    },
    {
      "objective": 1047245.0,
      "time": 20.371999979019165
    },
    {
      "objective": 1047331.0,
      "time": 21.26900005340576
    },
    {
      "objective": 1047387.0,
      "time": 21.45199990272522
    },
    {
      "objective": 1047870.0,
      "time": 21.52999997138977
    },
    {
      "objective": 1047874.0,
      "time": 22.10599994659424
    },
    {
      "objective": 1048358.0,
      "time": 22.852999925613403
    },
    {
      "objective": 1048590.0,
      "time": 22.888999938964844
    },
    {
      "objective": 1048824.0,
      "time": 23.47099995613098
    },
    {
      "objective": 1049313.0,
      "time": 23.82100009918213
    },
    {
      "objective": 1049824.0,
      "time": 23.947999954223633
    },
    {
      "objective": 1049867.0,
      "time": 24.109999895095825
    },
    {
      "objective": 1050421.0,
      "time": 24.27300000190735
    },
    {
      "objective": 1051876.0,
      "time": 24.65000009536743
    },
    {
      "objective": 1052456.0,
      "time": 25.795000076293945
    },
    {
      "objective": 1052504.0,
      "time": 26.703999996185303
    },
    {
      "objective": 1052507.0,
      "time": 29.04800009727478
    },
    {
      "objective": 1052512.0,
      "time": 30.378000020980835
    },
    {
      "objective": 1052524.0,
      "time": 32.59699988365173
    },
    {
      "objective": 1052540.0,
      "time": 32.70199990272522
    },
    {
      "objective": 1052546.0,
      "time": 32.77500009536743
    },
    {
      "objective": 1052686.0,
      "time": 32.86199998855591
    },
    {
      "objective": 1052687.0,
      "time": 33.28500008583069
    },
    {
      "objective": 1052705.0,
      "time": 34.2039999961853
    },
    {
      "objective": 1052718.0,
      "time": 37.081000089645386
    },
    {
      "objective": 1052726.0,
      "time": 38.1029999256134
    },
    {
      "objective": 1052850.0,
      "time": 39.632999897003174
    },
    {
      "objective": 1052875.0,
      "time": 40.39299988746643
    },
    {
      "objective": 1052876.0,
      "time": 40.99399995803833
    },
    {
      "objective": 1052878.0,
      "time": 41.24399995803833
    },
    {
      "objective": 1052897.0,
      "time": 41.776000022888184
    },
    {
      "objective": 1053026.0,
      "time": 41.950000047683716
    },
    {
      "objective": 1053043.0,
      "time": 42.3199999332428
    },
    {
      "objective": 1053058.0,
      "time": 42.664000034332275
    },
    {
      "objective": 1053062.0,
      "time": 43.47499990463257
    },
    {
      "objective": 1053290.0,
      "time": 43.62899994850159
    },
    {
      "objective": 1053294.0,
      "time": 43.76300001144409
    },
    {
      "objective": 1053695.0,
      "time": 45.93400001525879
    },
    {
      "objective": 1053716.0,
      "time": 47.740999937057495
    },
    {
      "objective": 1053853.0,
      "time": 48.575000047683716
    },
    {
      "objective": 1053893.0,
      "time": 50.12700009346008
    },
    {
      "objective": 1053903.0,
      "time": 50.39100003242493
    },
    {
      "objective": 1054146.0,
      "time": 51.72699999809265
    },
    {
      "objective": 1054147.0,
      "time": 52.11500000953674
    },
    {
      "objective": 1054150.0,
      "time": 52.83899998664856
    },
    {
      "objective": 1054177.0,
      "time": 55.062999963760376
    },
    {
      "objective": 1054186.0,
      "time": 57.42300009727478
    },
    {
      "objective": 1054192.0,
      "time": 57.609999895095825
    },
    {
      "objective": 1054207.0,
      "time": 58.31599998474121
    },
    {
      "objective": 1054211.0,
      "time": 58.73799991607666
    },
    {
      "objective": 1054229.0,
      "time": 62.54900002479553
    },
    {
      "objective": 1054237.0,
      "time": 64.00999999046326
    },
    {
      "objective": 1054276.0,
      "time": 82.375
    },
    {
      "objective": 1054300.0,
      "time": 82.72399997711182
    },
    {
      "objective": 1054321.0,
      "time": 83.75
    },
    {
      "objective": 1054326.0,
      "time": 88.6949999332428
    },
    {
      "objective": 1054337.0,
      "time": 90.17899990081787
    },
    {
      "objective": 1054369.0,
      "time": 90.90599989891052
    },
    {
      "objective": 1054374.0,
      "time": 91.07299995422363
    },
    {
      "objective": 1054377.0,
      "time": 91.99799990653992
    },
    {
      "objective": 1054379.0,
      "time": 96.68700003623962
    },
    {
      "objective": 1054413.0,
      "time": 103.73900008201599
    },
    {
      "objective": 1054496.0,
      "time": 104.19099998474121
    },
    {
      "objective": 1054501.0,
      "time": 104.62599992752075
    },
    {
      "objective": 1054503.0,
      "time": 104.95600008964539
    },
    {
      "objective": 1054504.0,
      "time": 106.58899998664856
    },
    {
      "objective": 1054514.0,
      "time": 106.99799990653992
    },
    {
      "objective": 1054527.0,
      "time": 107.1930000782013
    },
    {
      "objective": 1054528.0,
      "time": 108.38899993896484
    },
    {
      "objective": 1054546.0,
      "time": 108.57200002670288
    },
    {
      "objective": 1054558.0,
      "time": 108.70099997520447
    },
    {
      "objective": 1054634.0,
      "time": 109.96300005912781
    },
    {
      "objective": 1054635.0,
      "time": 110.25200009346008
    },
    {
      "objective": 1054637.0,
      "time": 111.7960000038147
    },
    {
      "objective": 1054658.0,
      "time": 113.45099997520447
    },
    {
      "objective": 1054659.0,
      "time": 114.28600001335144
    },
    {
      "objective": 1054660.0,
      "time": 114.35899996757507
    },
    {
      "objective": 1054665.0,
      "time": 115.29099988937378
    },
    {
      "objective": 1054686.0,
      "time": 116.11899995803833
    },
    {
      "objective": 1054688.0,
      "time": 124.17300009727478
    },
    {
      "objective": 1054701.0,
      "time": 125.25099992752075
    },
    {
      "objective": 1054703.0,
      "time": 125.63000011444092
    },
    {
      "objective": 1054993.0,
      "time": 134.62400007247925
    },
    {
      "objective": 1055002.0,
      "time": 135.33599996566772
    },
    {
      "objective": 1055003.0,
      "time": 135.5590000152588
    },
    {
      "objective": 1055005.0,
      "time": 140.36800003051758
    },
    {
      "objective": 1055076.0,
      "time": 149.79699993133545
    },
    {
      "objective": 1055077.0,
      "time": 150.19899988174438
    },
    {
      "objective": 1055083.0,
      "time": 150.28900003433228
    },
    {
      "objective": 1055107.0,
      "time": 150.48200011253357
    },
    {
      "objective": 1055128.0,
      "time": 151.36100006103516
    },
    {
      "objective": 1055147.0,
      "time": 154.98499989509583
    },
    {
      "objective": 1055157.0,
      "time": 164.6670000553131
    },
    {
      "objective": 1055161.0,
      "time": 166.5590000152588
    },
    {
      "objective": 1055221.0,
      "time": 170.46600008010864
    },
    {
      "objective": 1055234.0,
      "time": 171.00799989700317
    },
    {
      "objective": 1055312.0,
      "time": 173.13100004196167
    },
    {
      "objective": 1055325.0,
      "time": 173.84400010108948
    },
    {
      "objective": 1055326.0,
      "time": 177.69400000572205
    },
    {
      "objective": 1055327.0,
      "time": 180.30299997329712
    },
    {
      "objective": 1055338.0,
      "time": 182.03900003433228
    },
    {
      "objective": 1055341.0,
      "time": 200.6619999408722
    },
    {
      "objective": 1055343.0,
      "time": 222.65300011634827
    },
    {
      "objective": 1055376.0,
      "time": 223.9630000591278
    },
    {
      "objective": 1055431.0,
      "time": 224.55200004577637
    },
    {
      "objective": 1055450.0,
      "time": 225.26600003242493
    },
    {
      "objective": 1055514.0,
      "time": 226.25699996948242
    },
    {
      "objective": 1055566.0,
      "time": 232.12199997901917
    },
    {
      "objective": 1055674.0,
      "time": 232.44799995422363
    },
    {
      "objective": 1055702.0,
      "time": 232.94199991226196
    },
    {
      "objective": 1055704.0,
      "time": 234.33500003814697
    },
    {
      "objective": 1055761.0,
      "time": 234.3880000114441
    },
    {
      "objective": 1055766.0,
      "time": 235.94600009918213
    },
    {
      "objective": 1055805.0,
      "time": 243.51500010490417
    },
    {
      "objective": 1055813.0,
      "time": 261.68499994277954
    },
    {
      "objective": 1055816.0,
      "time": 274.0569999217987
    },
    {
      "objective": 1055859.0,
      "time": 280.6949999332428
    },
    {
      "objective": 1055870.0,
      "time": 281.54500007629395
    },
    {
      "objective": 1055923.0,
      "time": 281.67000007629395
    },
    {
      "objective": 1055955.0,
      "time": 283.44000005722046
    },
    {
      "objective": 1056000.0,
      "time": 284.42700004577637
    },
    {
      "objective": 1056034.0,
      "time": 286.9539999961853
    },
    {
      "objective": 1056041.0,
      "time": 287.1909999847412
    },
    {
      "objective": 1056042.0,
      "time": 291.4649999141693
    },
    {
      "objective": 1056052.0,
      "time": 293.2920000553131
    }
  ],
  "instance": "density\u003dMEDIUM_nInventory\u003d20_nHours\u003d5_seed\u003d4",
  "additionalInformation": {
    "settings": {
      "searchMode": "BEST_IMPROVEMENT",
      "timeLimit": 300,
      "localSearchSettings": {
        "moves": [
          "insert",
          "outOfPool",
          "interSwap",
          "shift",
          "transfer",
          "intraSwap"
        ],
        "neighborhoodSkipProbability": 0.5,
        "minProbability": 0.05,
        "updateProbabilitiesAtEveryNIter": 100
      },
      "constructiveHeuristicSettings": {
        "lowerBound": 0.5,
        "upperBound": 2.0
      },
      "alphaGenerator": {
        "alphaValues": [
          0.1,
          0.2,
          0.3,
          0.4,
          0.5,
          0.6,
          0.7,
          0.8,
          0.9
        ],
        "probabilities": [
          0.11416049149221079,
          0.1084184740883952,
          0.10961665765241917,
          0.11393385293173444,
          0.11280173069820812,
          0.11128166884728291,
          0.11143405333215764,
          0.11101540268370368,
          0.10733766827388813
        ],
        "totalQuality": [
          1.251783273E9,
          1.139755432E9,
          1.163132219E9,
          1.247361512E9,
          1.225273594E9,
          1.195616901E9,
          1.198589951E9,
          1.190421998E9,
          1.118668707E9
        ],
        "usageCount": [
          1188,
          1082,
          1104,
          1184,
          1163,
          1135,
          1139,
          1130,
          1062
        ],
        "totalIterations": 10187
      },
      "randomRunN": 1,
      "instancePath": "instances/density\u003dMEDIUM_nInventory\u003d20_nHours\u003d5_seed\u003d4.json"
    },
    "iterationsPerSecond": 33.95666666666666,
    "moveStatistics": {
      "stats": {
        "transfer": {
          "attempts": 384448,
          "successes": 236343,
          "totalRevenueGain": 2.59931061E8,
          "totalTimeNanos": 1208146487016
        },
        "intraSwap": {
          "attempts": 175580,
          "successes": 170966,
          "totalRevenueGain": 4.2482494E7,
          "totalTimeNanos": 282303201885
        },
        "shift": {
          "attempts": 169491,
          "successes": 158389,
          "totalRevenueGain": 3.7571122E7,
          "totalTimeNanos": 541780038970
        },
        "interSwap": {
          "attempts": 562851,
          "successes": 518697,
          "totalRevenueGain": 4.70803436E8,
          "totalTimeNanos": 1582206542445
        },
        "outOfPool": {
          "attempts": 424706,
          "successes": 322187,
          "totalRevenueGain": 3.10206425E8,
          "totalTimeNanos": 5013058491364
        },
        "insert": {
          "attempts": 144328,
          "successes": 7002,
          "totalRevenueGain": 1.2797888E7,
          "totalTimeNanos": 128104867188
        }
      }
    },
    "componentEfficacy": {
      "stats": {
        "CONSTRUCTIVE_HEURISTIC": {
          "callCount": 10187,
          "totalTimeNanos": 386605389355,
          "totalRevenueGain": 9.129941951E9
        },
        "LOCAL_SEARCH": {
          "callCount": 20371,
          "totalTimeNanos": 8756403021556,
          "totalRevenueGain": 1.133792426E9
        },
        "PATH_RELINKING": {
          "callCount": 10184,
          "totalTimeNanos": 155485372231,
          "totalRevenueGain": 4.6686921E8
        }
      }
    }
  }
}