{
  "bestSolution": {
    "revenue": 1444891
  },
  "checkPoints": [
    {
      "solution": {
        "revenue": 1239786
      },
      "time": 1.369999885559082
    },
    {
      "solution": {
        "revenue": 1252758
      },
      "time": 1.5209999084472656
    },
    {
      "solution": {
        "revenue": 1275651
      },
      "time": 1.5369999408721924
    },
    {
      "solution": {
        "revenue": 1320550
      },
      "time": 1.6530001163482666
    },
    {
      "solution": {
        "revenue": 1327646
      },
      "time": 1.88100004196167
    },
    {
      "solution": {
        "revenue": 1337914
      },
      "time": 1.8910000324249268
    },
    {
      "solution": {
        "revenue": 1353881
      },
      "time": 2.0
    },
    {
      "solution": {
        "revenue": 1357294
      },
      "time": 2.2839999198913574
    },
    {
      "solution": {
        "revenue": 1361502
      },
      "time": 2.303999900817871
    },
    {
      "solution": {
        "revenue": 1364275
      },
      "time": 2.427999973297119
    },
    {
      "solution": {
        "revenue": 1366002
      },
      "time": 2.49399995803833
    },
    {
      "solution": {
        "revenue": 1369075
      },
      "time": 2.5160000324249268
    },
    {
      "solution": {
        "revenue": 1374949
      },
      "time": 2.562999963760376
    },
    {
      "solution": {
        "revenue": 1375118
      },
      "time": 2.5759999752044678
    },
    {
      "solution": {
        "revenue": 1375779
      },
      "time": 2.5769999027252197
    },
    {
      "solution": {
        "revenue": 1381458
      },
      "time": 2.628000020980835
    },
    {
      "solution": {
        "revenue": 1383012
      },
      "time": 2.677000045776367
    },
    {
      "solution": {
        "revenue": 1383775
      },
      "time": 2.694999933242798
    },
    {
      "solution": {
        "revenue": 1383844
      },
      "time": 2.7290000915527344
    },
    {
      "solution": {
        "revenue": 1384242
      },
      "time": 2.7339999675750732
    },
    {
      "solution": {
        "revenue": 1385652
      },
      "time": 2.743000030517578
    },
    {
      "solution": {
        "revenue": 1385750
      },
      "time": 2.7890000343322754
    },
    {
      "solution": {
        "revenue": 1386092
      },
      "time": 2.819000005722046
    },
    {
      "solution": {
        "revenue": 1386220
      },
      "time": 2.8519999980926514
    },
    {
      "solution": {
        "revenue": 1387207
      },
      "time": 2.9040000438690186
    },
    {
      "solution": {
        "revenue": 1387822
      },
      "time": 2.9230000972747803
    },
    {
      "solution": {
        "revenue": 1387928
      },
      "time": 2.9230000972747803
    },
    {
      "solution": {
        "revenue": 1388556
      },
      "time": 3.0199999809265137
    },
    {
      "solution": {
        "revenue": 1389212
      },
      "time": 3.0380001068115234
    },
    {
      "solution": {
        "revenue": 1391575
      },
      "time": 3.1010000705718994
    },
    {
      "solution": {
        "revenue": 1392352
      },
      "time": 3.1510000228881836
    },
    {
      "solution": {
        "revenue": 1392525
      },
      "time": 3.1630001068115234
    },
    {
      "solution": {
        "revenue": 1393078
      },
      "time": 3.1710000038146973
    },
    {
      "solution": {
        "revenue": 1393182
      },
      "time": 3.2019999027252197
    },
    {
      "solution": {
        "revenue": 1393240
      },
      "time": 3.203000068664551
    },
    {
      "solution": {
        "revenue": 1393753
      },
      "time": 3.2119998931884766
    },
    {
      "solution": {
        "revenue": 1394112
      },
      "time": 3.3480000495910645
    },
    {
      "solution": {
        "revenue": 1396328
      },
      "time": 3.3550000190734863
    },
    {
      "solution": {
        "revenue": 1396724
      },
      "time": 3.388000011444092
    },
    {
      "solution": {
        "revenue": 1397377
      },
      "time": 3.4049999713897705
    },
    {
      "solution": {
        "revenue": 1398496
      },
      "time": 3.437000036239624
    },
    {
      "solution": {
        "revenue": 1399919
      },
      "time": 3.499000072479248
    },
    {
      "solution": {
        "revenue": 1403886
      },
      "time": 3.5880000591278076
    },
    {
      "solution": {
        "revenue": 1403940
      },
      "time": 3.6429998874664307
    },
    {
      "solution": {
        "revenue": 1404003
      },
      "time": 3.681999921798706
    },
    {
      "solution": {
        "revenue": 1404380
      },
      "time": 3.697999954223633
    },
    {
      "solution": {
        "revenue": 1404382
      },
      "time": 3.7130000591278076
    },
    {
      "solution": {
        "revenue": 1404852
      },
      "time": 3.7290000915527344
    },
    {
      "solution": {
        "revenue": 1404932
      },
      "time": 3.734999895095825
    },
    {
      "solution": {
        "revenue": 1404933
      },
      "time": 3.822000026702881
    },
    {
      "solution": {
        "revenue": 1405577
      },
      "time": 3.8369998931884766
    },
    {
      "solution": {
        "revenue": 1406763
      },
      "time": 3.9709999561309814
    },
    {
      "solution": {
        "revenue": 1407859
      },
      "time": 3.993000030517578
    },
    {
      "solution": {
        "revenue": 1408353
      },
      "time": 4.161999940872192
    },
    {
      "solution": {
        "revenue": 1408395
      },
      "time": 4.292999982833862
    },
    {
      "solution": {
        "revenue": 1410145
      },
      "time": 4.394999980926514
    },
    {
      "solution": {
        "revenue": 1410802
      },
      "time": 4.395999908447266
    },
    {
      "solution": {
        "revenue": 1411238
      },
      "time": 4.479000091552734
    },
    {
      "solution": {
        "revenue": 1411326
      },
      "time": 4.698999881744385
    },
    {
      "solution": {
        "revenue": 1412974
      },
      "time": 4.739000082015991
    },
    {
      "solution": {
        "revenue": 1413041
      },
      "time": 4.861000061035156
    },
    {
      "solution": {
        "revenue": 1413262
      },
      "time": 5.003000020980835
    },
    {
      "solution": {
        "revenue": 1414027
      },
      "time": 5.302000045776367
    },
    {
      "solution": {
        "revenue": 1414647
      },
      "time": 5.7850000858306885
    },
    {
      "solution": {
        "revenue": 1414976
      },
      "time": 5.937000036239624
    },
    {
      "solution": {
        "revenue": 1415004
      },
      "time": 5.971999883651733
    },
    {
      "solution": {
        "revenue": 1416977
      },
      "time": 6.00600004196167
    },
    {
      "solution": {
        "revenue": 1416978
      },
      "time": 6.111999988555908
    },
    {
      "solution": {
        "revenue": 1417405
      },
      "time": 6.2200000286102295
    },
    {
      "solution": {
        "revenue": 1417412
      },
      "time": 6.242000102996826
    },
    {
      "solution": {
        "revenue": 1417904
      },
      "time": 6.26200008392334
    },
    {
      "solution": {
        "revenue": 1418443
      },
      "time": 6.263000011444092
    },
    {
      "solution": {
        "revenue": 1419286
      },
      "time": 6.357000112533569
    },
    {
      "solution": {
        "revenue": 1420465
      },
      "time": 6.6579999923706055
    },
    {
      "solution": {
        "revenue": 1420677
      },
      "time": 6.707000017166138
    },
    {
      "solution": {
        "revenue": 1421482
      },
      "time": 6.742000102996826
    },
    {
      "solution": {
        "revenue": 1421489
      },
      "time": 6.750999927520752
    },
    {
      "solution": {
        "revenue": 1422135
      },
      "time": 6.936000108718872
    },
    {
      "solution": {
        "revenue": 1422458
      },
      "time": 7.3399999141693115
    },
    {
      "solution": {
        "revenue": 1424807
      },
      "time": 7.418999910354614
    },
    {
      "solution": {
        "revenue": 1425275
      },
      "time": 7.436000108718872
    },
    {
      "solution": {
        "revenue": 1426138
      },
      "time": 7.477999925613403
    },
    {
      "solution": {
        "revenue": 1426436
      },
      "time": 7.516999959945679
    },
    {
      "solution": {
        "revenue": 1426544
      },
      "time": 7.624000072479248
    },
    {
      "solution": {
        "revenue": 1426670
      },
      "time": 7.634999990463257
    },
    {
      "solution": {
        "revenue": 1426788
      },
      "time": 7.642999887466431
    },
    {
      "solution": {
        "revenue": 1427118
      },
      "time": 7.711999893188477
    },
    {
      "solution": {
        "revenue": 1427280
      },
      "time": 7.769000053405762
    },
    {
      "solution": {
        "revenue": 1427375
      },
      "time": 7.808000087738037
    },
    {
      "solution": {
        "revenue": 1429064
      },
      "time": 7.851000070571899
    },
    {
      "solution": {
        "revenue": 1429600
      },
      "time": 7.9709999561309814
    },
    {
      "solution": {
        "revenue": 1429611
      },
      "time": 7.977999925613403
    },
    {
      "solution": {
        "revenue": 1429770
      },
      "time": 7.990999937057495
    },
    {
      "solution": {
        "revenue": 1429774
      },
      "time": 8.005000114440918
    },
    {
      "solution": {
        "revenue": 1430098
      },
      "time": 8.062999963760376
    },
    {
      "solution": {
        "revenue": 1430947
      },
      "time": 8.104000091552734
    },
    {
      "solution": {
        "revenue": 1431205
      },
      "time": 8.53600001335144
    },
    {
      "solution": {
        "revenue": 1431357
      },
      "time": 8.585999965667725
    },
    {
      "solution": {
        "revenue": 1431377
      },
      "time": 8.622999906539917
    },
    {
      "solution": {
        "revenue": 1431464
      },
      "time": 8.930999994277954
    },
    {
      "solution": {
        "revenue": 1431568
      },
      "time": 9.0
    },
    {
      "solution": {
        "revenue": 1431768
      },
      "time": 9.085000038146973
    },
    {
      "solution": {
        "revenue": 1431770
      },
      "time": 9.128999948501587
    },
    {
      "solution": {
        "revenue": 1431771
      },
      "time": 9.279000043869019
    },
    {
      "solution": {
        "revenue": 1432106
      },
      "time": 9.38100004196167
    },
    {
      "solution": {
        "revenue": 1432111
      },
      "time": 9.500999927520752
    },
    {
      "solution": {
        "revenue": 1432112
      },
      "time": 9.658999919891357
    },
    {
      "solution": {
        "revenue": 1432206
      },
      "time": 9.727999925613403
    },
    {
      "solution": {
        "revenue": 1432248
      },
      "time": 9.746000051498413
    },
    {
      "solution": {
        "revenue": 1432255
      },
      "time": 9.802000045776367
    },
    {
      "solution": {
        "revenue": 1432257
      },
      "time": 9.818000078201294
    },
    {
      "solution": {
        "revenue": 1432670
      },
      "time": 9.82800006866455
    },
    {
      "solution": {
        "revenue": 1433790
      },
      "time": 10.338000059127808
    },
    {
      "solution": {
        "revenue": 1434010
      },
      "time": 10.848999977111816
    },
    {
      "solution": {
        "revenue": 1434011
      },
      "time": 10.891999959945679
    },
    {
      "solution": {
        "revenue": 1434556
      },
      "time": 10.930000066757202
    },
    {
      "solution": {
        "revenue": 1434644
      },
      "time": 11.430999994277954
    },
    {
      "solution": {
        "revenue": 1434699
      },
      "time": 11.742000102996826
    },
    {
      "solution": {
        "revenue": 1435333
      },
      "time": 11.803999900817871
    },
    {
      "solution": {
        "revenue": 1435578
      },
      "time": 12.230999946594238
    },
    {
      "solution": {
        "revenue": 1436199
      },
      "time": 12.250999927520752
    },
    {
      "solution": {
        "revenue": 1436525
      },
      "time": 12.315999984741211
    },
    {
      "solution": {
        "revenue": 1436602
      },
      "time": 12.525000095367432
    },
    {
      "solution": {
        "revenue": 1436603
      },
      "time": 12.542999982833862
    },
    {
      "solution": {
        "revenue": 1436653
      },
      "time": 12.625999927520752
    },
    {
      "solution": {
        "revenue": 1436870
      },
      "time": 12.80299997329712
    },
    {
      "solution": {
        "revenue": 1437147
      },
      "time": 12.846999883651733
    },
    {
      "solution": {
        "revenue": 1437239
      },
      "time": 12.861000061035156
    },
    {
      "solution": {
        "revenue": 1437297
      },
      "time": 12.918999910354614
    },
    {
      "solution": {
        "revenue": 1437736
      },
      "time": 12.956000089645386
    },
    {
      "solution": {
        "revenue": 1437754
      },
      "time": 13.023000001907349
    },
    {
      "solution": {
        "revenue": 1439229
      },
      "time": 13.101999998092651
    },
    {
      "solution": {
        "revenue": 1440242
      },
      "time": 13.569000005722046
    },
    {
      "solution": {
        "revenue": 1440388
      },
      "time": 13.82699990272522
    },
    {
      "solution": {
        "revenue": 1440551
      },
      "time": 13.98200011253357
    },
    {
      "solution": {
        "revenue": 1440692
      },
      "time": 14.066999912261963
    },
    {
      "solution": {
        "revenue": 1440780
      },
      "time": 14.365999937057495
    },
    {
      "solution": {
        "revenue": 1441307
      },
      "time": 14.614000082015991
    },
    {
      "solution": {
        "revenue": 1441321
      },
      "time": 14.76200008392334
    },
    {
      "solution": {
        "revenue": 1441623
      },
      "time": 15.319000005722046
    },
    {
      "solution": {
        "revenue": 1441771
      },
      "time": 15.469000101089478
    },
    {
      "solution": {
        "revenue": 1441923
      },
      "time": 17.581000089645386
    },
    {
      "solution": {
        "revenue": 1442065
      },
      "time": 18.602999925613403
    },
    {
      "solution": {
        "revenue": 1442238
      },
      "time": 21.89400005340576
    },
    {
      "solution": {
        "revenue": 1442437
      },
      "time": 23.26900005340576
    },
    {
      "solution": {
        "revenue": 1442438
      },
      "time": 24.355000019073486
    },
    {
      "solution": {
        "revenue": 1442439
      },
      "time": 24.52999997138977
    },
    {
      "solution": {
        "revenue": 1442566
      },
      "time": 24.568000078201294
    },
    {
      "solution": {
        "revenue": 1442567
      },
      "time": 26.219000101089478
    },
    {
      "solution": {
        "revenue": 1442612
      },
      "time": 29.76099991798401
    },
    {
      "solution": {
        "revenue": 1442631
      },
      "time": 32.437999963760376
    },
    {
      "solution": {
        "revenue": 1442665
      },
      "time": 38.242000102996826
    },
    {
      "solution": {
        "revenue": 1442666
      },
      "time": 48.365999937057495
    },
    {
      "solution": {
        "revenue": 1442668
      },
      "time": 81.38199996948242
    },
    {
      "solution": {
        "revenue": 1442687
      },
      "time": 154.34500002861023
    },
    {
      "solution": {
        "revenue": 1442720
      },
      "time": 154.96900010108948
    },
    {
      "solution": {
        "revenue": 1442811
      },
      "time": 154.97199988365173
    },
    {
      "solution": {
        "revenue": 1443197
      },
      "time": 155.11700010299683
    },
    {
      "solution": {
        "revenue": 1443272
      },
      "time": 155.13899993896484
    },
    {
      "solution": {
        "revenue": 1443273
      },
      "time": 155.14800000190735
    },
    {
      "solution": {
        "revenue": 1443275
      },
      "time": 155.43099999427795
    },
    {
      "solution": {
        "revenue": 1443276
      },
      "time": 156.2149999141693
    },
    {
      "solution": {
        "revenue": 1443288
      },
      "time": 156.64299988746643
    },
    {
      "solution": {
        "revenue": 1443422
      },
      "time": 156.78600001335144
    },
    {
      "solution": {
        "revenue": 1444142
      },
      "time": 166.33500003814697
    },
    {
      "solution": {
        "revenue": 1444247
      },
      "time": 166.3529999256134
    },
    {
      "solution": {
        "revenue": 1444248
      },
      "time": 166.52300000190735
    },
    {
      "solution": {
        "revenue": 1444841
      },
      "time": 166.56100010871887
    },
    {
      "solution": {
        "revenue": 1444888
      },
      "time": 167.02600002288818
    },
    {
      "solution": {
        "revenue": 1444889
      },
      "time": 168.91599988937378
    },
    {
      "solution": {
        "revenue": 1444890
      },
      "time": 170.34599995613098
    },
    {
      "solution": {
        "revenue": 1444891
      },
      "time": 213.67000007629395
    }
  ],
  "instance": "density\u003dHIGH_nInventory\u003d20_nHours\u003d5_seed\u003d2",
  "additionalInformation": {
    "settings": {
      "searchMode": "FIRST_IMPROVEMENT",
      "timeLimit": 300,
      "localSearchSettings": {
        "moves": [
          "insert",
          "outOfPool",
          "interSwap",
          "shift",
          "transfer",
          "intraSwap"
        ],
        "neighborhoodSkipProbability": 0.25
      },
      "constructiveHeuristicSettings": {
        "lowerBound": 0.5,
        "upperBound": 2.0
      },
      "alphaGenerator": {
        "alpha": 0.25
      },
      "randomRunN": 0,
      "instancePath": "instances/density\u003dHIGH_nInventory\u003d20_nHours\u003d5_seed\u003d2.json"
    },
    "iterationsPerSecond": 668.6633333333333
  }
}