{
  "bestSolution": {
    "revenue": 702061.8699878183
  },
  "checkPoints": [
    {
      "solution": {
        "revenue": 478578.24041257706
      },
      "time": 0.0
    },
    {
      "solution": {
        "revenue": 561417.4492574765
      },
      "time": 0.0
    },
    {
      "solution": {
        "revenue": 520740.39192917757
      },
      "time": 1.0
    },
    {
      "solution": {
        "revenue": 586119.46582098
      },
      "time": 5.0
    },
    {
      "solution": {
        "revenue": 586160.7360721584
      },
      "time": 5.0
    },
    {
      "solution": {
        "revenue": 520404.9983591945
      },
      "time": 8.0
    },
    {
      "solution": {
        "revenue": 586780.696525535
      },
      "time": 9.0
    },
    {
      "solution": {
        "revenue": 598584.7875907192
      },
      "time": 14.0
    },
    {
      "solution": {
        "revenue": 601429.1832879911
      },
      "time": 24.0
    },
    {
      "solution": {
        "revenue": 586097.6024652346
      },
      "time": 24.0
    },
    {
      "solution": {
        "revenue": 602555.3052323057
      },
      "time": 24.0
    },
    {
      "solution": {
        "revenue": 606031.8251300438
      },
      "time": 25.0
    },
    {
      "solution": {
        "revenue": 604812.1387897136
      },
      "time": 25.0
    },
    {
      "solution": {
        "revenue": 604876.8552825266
      },
      "time": 25.0
    },
    {
      "solution": {
        "revenue": 619823.1914239838
      },
      "time": 30.0
    },
    {
      "solution": {
        "revenue": 566177.5529836306
      },
      "time": 33.0
    },
    {
      "solution": {
        "revenue": 566559.979300507
      },
      "time": 33.0
    },
    {
      "solution": {
        "revenue": 568921.4723852661
      },
      "time": 33.0
    },
    {
      "solution": {
        "revenue": 609295.7038461643
      },
      "time": 35.0
    },
    {
      "solution": {
        "revenue": 601740.4248915197
      },
      "time": 35.0
    },
    {
      "solution": {
        "revenue": 602135.1059855135
      },
      "time": 35.0
    },
    {
      "solution": {
        "revenue": 626546.5269105367
      },
      "time": 36.0
    },
    {
      "solution": {
        "revenue": 623367.6987579472
      },
      "time": 37.0
    },
    {
      "solution": {
        "revenue": 614614.1113449264
      },
      "time": 37.0
    },
    {
      "solution": {
        "revenue": 614840.8826455273
      },
      "time": 37.0
    },
    {
      "solution": {
        "revenue": 634396.4999376556
      },
      "time": 40.0
    },
    {
      "solution": {
        "revenue": 561115.0591980711
      },
      "time": 40.0
    },
    {
      "solution": {
        "revenue": 634626.8510399476
      },
      "time": 41.0
    },
    {
      "solution": {
        "revenue": 635623.8743014039
      },
      "time": 41.0
    },
    {
      "solution": {
        "revenue": 601236.5011309324
      },
      "time": 41.0
    },
    {
      "solution": {
        "revenue": 630699.2925390257
      },
      "time": 44.0
    },
    {
      "solution": {
        "revenue": 634559.3628141026
      },
      "time": 44.0
    },
    {
      "solution": {
        "revenue": 634774.5807715439
      },
      "time": 44.0
    },
    {
      "solution": {
        "revenue": 593805.5254573715
      },
      "time": 44.0
    },
    {
      "solution": {
        "revenue": 593805.5254573715
      },
      "time": 44.0
    },
    {
      "solution": {
        "revenue": 639210.4404247552
      },
      "time": 44.0
    },
    {
      "solution": {
        "revenue": 642818.2639810538
      },
      "time": 44.0
    },
    {
      "solution": {
        "revenue": 641515.9531705575
      },
      "time": 44.0
    },
    {
      "solution": {
        "revenue": 643338.8857001502
      },
      "time": 45.0
    },
    {
      "solution": {
        "revenue": 571447.0367022854
      },
      "time": 48.0
    },
    {
      "solution": {
        "revenue": 632724.0783640981
      },
      "time": 48.0
    },
    {
      "solution": {
        "revenue": 634108.0635096248
      },
      "time": 48.0
    },
    {
      "solution": {
        "revenue": 636863.3119633431
      },
      "time": 48.0
    },
    {
      "solution": {
        "revenue": 488579.6028129542
      },
      "time": 48.0
    },
    {
      "solution": {
        "revenue": 638382.8627144065
      },
      "time": 49.0
    },
    {
      "solution": {
        "revenue": 537961.4215873384
      },
      "time": 49.0
    },
    {
      "solution": {
        "revenue": 661323.4746696192
      },
      "time": 50.0
    },
    {
      "solution": {
        "revenue": 648858.9175940274
      },
      "time": 50.0
    },
    {
      "solution": {
        "revenue": 646672.8513316476
      },
      "time": 51.0
    },
    {
      "solution": {
        "revenue": 646786.4796934174
      },
      "time": 51.0
    },
    {
      "solution": {
        "revenue": 540685.1788419194
      },
      "time": 51.0
    },
    {
      "solution": {
        "revenue": 542630.5999056224
      },
      "time": 51.0
    },
    {
      "solution": {
        "revenue": 545931.1467293418
      },
      "time": 51.0
    },
    {
      "solution": {
        "revenue": 546040.4467730507
      },
      "time": 51.0
    },
    {
      "solution": {
        "revenue": 546040.4467730507
      },
      "time": 51.0
    },
    {
      "solution": {
        "revenue": 547241.1347505766
      },
      "time": 52.0
    },
    {
      "solution": {
        "revenue": 548577.7111388189
      },
      "time": 52.0
    },
    {
      "solution": {
        "revenue": 551889.9784023677
      },
      "time": 53.0
    },
    {
      "solution": {
        "revenue": 553413.919400142
      },
      "time": 53.0
    },
    {
      "solution": {
        "revenue": 553980.5731330811
      },
      "time": 53.0
    },
    {
      "solution": {
        "revenue": 634609.7646890766
      },
      "time": 55.0
    },
    {
      "solution": {
        "revenue": 549002.213972927
      },
      "time": 55.0
    },
    {
      "solution": {
        "revenue": 550672.0814299126
      },
      "time": 56.0
    },
    {
      "solution": {
        "revenue": 551916.2223186323
      },
      "time": 56.0
    },
    {
      "solution": {
        "revenue": 552014.5638337188
      },
      "time": 56.0
    },
    {
      "solution": {
        "revenue": 552342.861553516
      },
      "time": 56.0
    },
    {
      "solution": {
        "revenue": 552072.7070185691
      },
      "time": 57.0
    },
    {
      "solution": {
        "revenue": 552072.7070185691
      },
      "time": 57.0
    },
    {
      "solution": {
        "revenue": 317679.8353801624
      },
      "time": 57.0
    },
    {
      "solution": {
        "revenue": 664534.308527835
      },
      "time": 57.0
    },
    {
      "solution": {
        "revenue": 666609.9075634954
      },
      "time": 58.0
    },
    {
      "solution": {
        "revenue": 665332.9787772726
      },
      "time": 58.0
    },
    {
      "solution": {
        "revenue": 475779.3228259257
      },
      "time": 60.0
    },
    {
      "solution": {
        "revenue": 480947.6824990718
      },
      "time": 60.0
    },
    {
      "solution": {
        "revenue": 676922.9806469416
      },
      "time": 60.0
    },
    {
      "solution": {
        "revenue": 502280.70484447613
      },
      "time": 61.0
    },
    {
      "solution": {
        "revenue": 501203.9277106977
      },
      "time": 61.0
    },
    {
      "solution": {
        "revenue": 657227.8303501444
      },
      "time": 62.0
    },
    {
      "solution": {
        "revenue": 666140.2613156262
      },
      "time": 62.0
    },
    {
      "solution": {
        "revenue": 667462.1477508558
      },
      "time": 62.0
    },
    {
      "solution": {
        "revenue": 661477.582993013
      },
      "time": 62.0
    },
    {
      "solution": {
        "revenue": 534760.1686672213
      },
      "time": 62.0
    },
    {
      "solution": {
        "revenue": 670415.871155944
      },
      "time": 62.0
    },
    {
      "solution": {
        "revenue": 672469.6325791419
      },
      "time": 62.0
    },
    {
      "solution": {
        "revenue": 344244.3042123188
      },
      "time": 63.0
    },
    {
      "solution": {
        "revenue": 673398.9014420556
      },
      "time": 64.0
    },
    {
      "solution": {
        "revenue": 675330.0503491346
      },
      "time": 64.0
    },
    {
      "solution": {
        "revenue": 675720.1442182431
      },
      "time": 64.0
    },
    {
      "solution": {
        "revenue": 676073.6275389199
      },
      "time": 64.0
    },
    {
      "solution": {
        "revenue": 675590.1012075776
      },
      "time": 64.0
    },
    {
      "solution": {
        "revenue": 677483.6348341205
      },
      "time": 64.0
    },
    {
      "solution": {
        "revenue": 686690.6263621853
      },
      "time": 65.0
    },
    {
      "solution": {
        "revenue": 466750.2897609234
      },
      "time": 66.0
    },
    {
      "solution": {
        "revenue": 669679.0218959905
      },
      "time": 67.0
    },
    {
      "solution": {
        "revenue": 670361.2030784572
      },
      "time": 67.0
    },
    {
      "solution": {
        "revenue": 668439.6665158273
      },
      "time": 68.0
    },
    {
      "solution": {
        "revenue": 670334.3626332822
      },
      "time": 68.0
    },
    {
      "solution": {
        "revenue": 669575.0073741868
      },
      "time": 68.0
    },
    {
      "solution": {
        "revenue": 669576.3708479957
      },
      "time": 68.0
    },
    {
      "solution": {
        "revenue": 597986.2090608234
      },
      "time": 68.0
    },
    {
      "solution": {
        "revenue": 598993.6265303217
      },
      "time": 68.0
    },
    {
      "solution": {
        "revenue": 601483.4934463729
      },
      "time": 68.0
    },
    {
      "solution": {
        "revenue": 470677.58584518643
      },
      "time": 69.0
    },
    {
      "solution": {
        "revenue": 472085.5275030996
      },
      "time": 69.0
    },
    {
      "solution": {
        "revenue": 545242.883777172
      },
      "time": 70.0
    },
    {
      "solution": {
        "revenue": 680361.4472543686
      },
      "time": 73.0
    },
    {
      "solution": {
        "revenue": 686447.7330598362
      },
      "time": 74.0
    },
    {
      "solution": {
        "revenue": 708396.0410293281
      },
      "time": 74.0
    },
    {
      "solution": {
        "revenue": 616820.173674829
      },
      "time": 74.0
    },
    {
      "solution": {
        "revenue": 614117.6444575415
      },
      "time": 76.0
    },
    {
      "solution": {
        "revenue": 612444.1956594809
      },
      "time": 77.0
    },
    {
      "solution": {
        "revenue": 584111.0462780044
      },
      "time": 77.0
    },
    {
      "solution": {
        "revenue": 584193.8680105129
      },
      "time": 77.0
    },
    {
      "solution": {
        "revenue": 586002.0992795251
      },
      "time": 77.0
    },
    {
      "solution": {
        "revenue": 586251.5098626626
      },
      "time": 78.0
    },
    {
      "solution": {
        "revenue": 586272.0426547641
      },
      "time": 78.0
    },
    {
      "solution": {
        "revenue": 586305.4570644703
      },
      "time": 78.0
    },
    {
      "solution": {
        "revenue": 586305.4570644703
      },
      "time": 79.0
    },
    {
      "solution": {
        "revenue": 586524.9957529593
      },
      "time": 79.0
    },
    {
      "solution": {
        "revenue": 613941.3580945632
      },
      "time": 80.0
    },
    {
      "solution": {
        "revenue": 613989.2328771815
      },
      "time": 80.0
    },
    {
      "solution": {
        "revenue": 615759.5695687352
      },
      "time": 80.0
    },
    {
      "solution": {
        "revenue": 615941.6144053749
      },
      "time": 80.0
    },
    {
      "solution": {
        "revenue": 618203.1403480478
      },
      "time": 80.0
    },
    {
      "solution": {
        "revenue": 622101.2902281769
      },
      "time": 80.0
    },
    {
      "solution": {
        "revenue": 621733.8380490227
      },
      "time": 81.0
    },
    {
      "solution": {
        "revenue": 622253.637817375
      },
      "time": 81.0
    },
    {
      "solution": {
        "revenue": 622531.3115565609
      },
      "time": 81.0
    },
    {
      "solution": {
        "revenue": 622531.3115565609
      },
      "time": 82.0
    },
    {
      "solution": {
        "revenue": 622531.3115565609
      },
      "time": 82.0
    },
    {
      "solution": {
        "revenue": 622819.8952747801
      },
      "time": 82.0
    },
    {
      "solution": {
        "revenue": 623155.96698385
      },
      "time": 83.0
    },
    {
      "solution": {
        "revenue": 623493.0025354006
      },
      "time": 83.0
    },
    {
      "solution": {
        "revenue": 623494.6921048717
      },
      "time": 84.0
    },
    {
      "solution": {
        "revenue": 623269.3796993608
      },
      "time": 84.0
    },
    {
      "solution": {
        "revenue": 624208.4629839013
      },
      "time": 84.0
    },
    {
      "solution": {
        "revenue": 624343.7092995119
      },
      "time": 85.0
    },
    {
      "solution": {
        "revenue": 569928.2504380968
      },
      "time": 88.0
    },
    {
      "solution": {
        "revenue": 626164.1837386255
      },
      "time": 88.0
    },
    {
      "solution": {
        "revenue": 626152.6937907971
      },
      "time": 88.0
    },
    {
      "solution": {
        "revenue": 582293.7409439537
      },
      "time": 89.0
    },
    {
      "solution": {
        "revenue": 581364.7402162987
      },
      "time": 89.0
    },
    {
      "solution": {
        "revenue": 581504.1515832831
      },
      "time": 89.0
    },
    {
      "solution": {
        "revenue": 582909.9198902075
      },
      "time": 89.0
    },
    {
      "solution": {
        "revenue": 561254.0355187054
      },
      "time": 90.0
    },
    {
      "solution": {
        "revenue": 631300.277157404
      },
      "time": 91.0
    },
    {
      "solution": {
        "revenue": 561828.0922432683
      },
      "time": 91.0
    },
    {
      "solution": {
        "revenue": 557657.9464824777
      },
      "time": 92.0
    },
    {
      "solution": {
        "revenue": 691345.3114381406
      },
      "time": 92.0
    },
    {
      "solution": {
        "revenue": 495655.7498823894
      },
      "time": 93.0
    },
    {
      "solution": {
        "revenue": 558829.7676698602
      },
      "time": 93.0
    },
    {
      "solution": {
        "revenue": 559033.5418945965
      },
      "time": 94.0
    },
    {
      "solution": {
        "revenue": 559034.2331517435
      },
      "time": 95.0
    },
    {
      "solution": {
        "revenue": 559160.0756563391
      },
      "time": 95.0
    },
    {
      "solution": {
        "revenue": 559175.3233642477
      },
      "time": 96.0
    },
    {
      "solution": {
        "revenue": 559990.3637983068
      },
      "time": 96.0
    },
    {
      "solution": {
        "revenue": 656693.1668649656
      },
      "time": 97.0
    },
    {
      "solution": {
        "revenue": 560390.7216925244
      },
      "time": 97.0
    },
    {
      "solution": {
        "revenue": 693518.444905577
      },
      "time": 98.0
    },
    {
      "solution": {
        "revenue": 693741.99916669
      },
      "time": 99.0
    },
    {
      "solution": {
        "revenue": 694010.5194662955
      },
      "time": 99.0
    },
    {
      "solution": {
        "revenue": 631379.9036308014
      },
      "time": 100.0
    },
    {
      "solution": {
        "revenue": 630026.6702469543
      },
      "time": 101.0
    },
    {
      "solution": {
        "revenue": 630119.1571047199
      },
      "time": 101.0
    },
    {
      "solution": {
        "revenue": 630132.1325021844
      },
      "time": 101.0
    },
    {
      "solution": {
        "revenue": 630194.403423435
      },
      "time": 101.0
    },
    {
      "solution": {
        "revenue": 693854.144012053
      },
      "time": 101.0
    },
    {
      "solution": {
        "revenue": 630761.6679838863
      },
      "time": 101.0
    },
    {
      "solution": {
        "revenue": 631910.6627667246
      },
      "time": 102.0
    },
    {
      "solution": {
        "revenue": 697295.8912423478
      },
      "time": 103.0
    },
    {
      "solution": {
        "revenue": 693811.7943623472
      },
      "time": 103.0
    },
    {
      "solution": {
        "revenue": 692330.2261765545
      },
      "time": 104.0
    },
    {
      "solution": {
        "revenue": 692871.3863050601
      },
      "time": 104.0
    },
    {
      "solution": {
        "revenue": 693100.7572884281
      },
      "time": 106.0
    },
    {
      "solution": {
        "revenue": 693234.7661184197
      },
      "time": 106.0
    },
    {
      "solution": {
        "revenue": 693615.4663898001
      },
      "time": 106.0
    },
    {
      "solution": {
        "revenue": 693929.9817895112
      },
      "time": 107.0
    },
    {
      "solution": {
        "revenue": 682234.1264477411
      },
      "time": 107.0
    },
    {
      "solution": {
        "revenue": 682349.0259260249
      },
      "time": 107.0
    },
    {
      "solution": {
        "revenue": 682338.0601386735
      },
      "time": 109.0
    },
    {
      "solution": {
        "revenue": 682818.4665297063
      },
      "time": 109.0
    },
    {
      "solution": {
        "revenue": 674250.7313439663
      },
      "time": 112.0
    },
    {
      "solution": {
        "revenue": 676427.6299909008
      },
      "time": 112.0
    },
    {
      "solution": {
        "revenue": 676460.3176158116
      },
      "time": 112.0
    },
    {
      "solution": {
        "revenue": 676480.8353797909
      },
      "time": 114.0
    },
    {
      "solution": {
        "revenue": 678218.3184805206
      },
      "time": 115.0
    },
    {
      "solution": {
        "revenue": 678482.8061367226
      },
      "time": 115.0
    },
    {
      "solution": {
        "revenue": 679127.9424872057
      },
      "time": 115.0
    },
    {
      "solution": {
        "revenue": 679219.002074595
      },
      "time": 117.0
    },
    {
      "solution": {
        "revenue": 680044.1608485198
      },
      "time": 118.0
    },
    {
      "solution": {
        "revenue": 680445.5977400286
      },
      "time": 118.0
    },
    {
      "solution": {
        "revenue": 681099.3865683669
      },
      "time": 119.0
    },
    {
      "solution": {
        "revenue": 567394.3253770743
      },
      "time": 119.0
    },
    {
      "solution": {
        "revenue": 567555.7706340109
      },
      "time": 119.0
    },
    {
      "solution": {
        "revenue": 566205.7080092164
      },
      "time": 121.0
    },
    {
      "solution": {
        "revenue": 566680.0918437857
      },
      "time": 121.0
    },
    {
      "solution": {
        "revenue": 567124.8375950259
      },
      "time": 122.0
    },
    {
      "solution": {
        "revenue": 565073.0452206015
      },
      "time": 122.0
    },
    {
      "solution": {
        "revenue": 565130.3881579426
      },
      "time": 122.0
    },
    {
      "solution": {
        "revenue": 565202.8733145285
      },
      "time": 123.0
    },
    {
      "solution": {
        "revenue": 651938.7040061278
      },
      "time": 124.0
    },
    {
      "solution": {
        "revenue": 652273.6706375488
      },
      "time": 125.0
    },
    {
      "solution": {
        "revenue": 652198.2316889464
      },
      "time": 126.0
    },
    {
      "solution": {
        "revenue": 652500.2069960735
      },
      "time": 126.0
    },
    {
      "solution": {
        "revenue": 652500.2069960735
      },
      "time": 127.0
    },
    {
      "solution": {
        "revenue": 652505.1690121143
      },
      "time": 127.0
    },
    {
      "solution": {
        "revenue": 652512.391265035
      },
      "time": 129.0
    },
    {
      "solution": {
        "revenue": 653038.4120194258
      },
      "time": 129.0
    },
    {
      "solution": {
        "revenue": 653092.0317759583
      },
      "time": 130.0
    },
    {
      "solution": {
        "revenue": 653107.2751067439
      },
      "time": 130.0
    },
    {
      "solution": {
        "revenue": 642088.6547749778
      },
      "time": 131.0
    },
    {
      "solution": {
        "revenue": 642725.5978442826
      },
      "time": 132.0
    },
    {
      "solution": {
        "revenue": 643025.3904990348
      },
      "time": 134.0
    },
    {
      "solution": {
        "revenue": 643036.2996391194
      },
      "time": 134.0
    },
    {
      "solution": {
        "revenue": 643080.8521853941
      },
      "time": 135.0
    },
    {
      "solution": {
        "revenue": 643182.5358162577
      },
      "time": 135.0
    },
    {
      "solution": {
        "revenue": 643481.4207286553
      },
      "time": 137.0
    },
    {
      "solution": {
        "revenue": 640883.776971217
      },
      "time": 138.0
    },
    {
      "solution": {
        "revenue": 641079.0958710125
      },
      "time": 139.0
    },
    {
      "solution": {
        "revenue": 643780.8303486705
      },
      "time": 139.0
    },
    {
      "solution": {
        "revenue": 643833.4710886959
      },
      "time": 140.0
    },
    {
      "solution": {
        "revenue": 643941.5860263573
      },
      "time": 141.0
    },
    {
      "solution": {
        "revenue": 643969.8689524111
      },
      "time": 143.0
    },
    {
      "solution": {
        "revenue": 720738.0130552478
      },
      "time": 143.0
    },
    {
      "solution": {
        "revenue": 644184.5930974279
      },
      "time": 144.0
    },
    {
      "solution": {
        "revenue": 720826.2975831422
      },
      "time": 145.0
    },
    {
      "solution": {
        "revenue": 720716.6506524371
      },
      "time": 145.0
    },
    {
      "solution": {
        "revenue": 720566.7445130104
      },
      "time": 146.0
    },
    {
      "solution": {
        "revenue": 644422.4820715475
      },
      "time": 147.0
    },
    {
      "solution": {
        "revenue": 644516.7568381472
      },
      "time": 147.0
    },
    {
      "solution": {
        "revenue": 720955.5789379327
      },
      "time": 147.0
    },
    {
      "solution": {
        "revenue": 720938.3724674896
      },
      "time": 148.0
    },
    {
      "solution": {
        "revenue": 679758.0176198652
      },
      "time": 148.0
    },
    {
      "solution": {
        "revenue": 679913.5769230516
      },
      "time": 149.0
    },
    {
      "solution": {
        "revenue": 680155.3868145106
      },
      "time": 151.0
    },
    {
      "solution": {
        "revenue": 680160.0089469518
      },
      "time": 152.0
    },
    {
      "solution": {
        "revenue": 680296.3180280225
      },
      "time": 153.0
    },
    {
      "solution": {
        "revenue": 680297.6994480357
      },
      "time": 153.0
    },
    {
      "solution": {
        "revenue": 680342.2519943104
      },
      "time": 153.0
    },
    {
      "solution": {
        "revenue": 681269.5588483233
      },
      "time": 153.0
    },
    {
      "solution": {
        "revenue": 681380.9402140102
      },
      "time": 153.0
    },
    {
      "solution": {
        "revenue": 681579.1511154361
      },
      "time": 157.0
    },
    {
      "solution": {
        "revenue": 681650.0765571994
      },
      "time": 158.0
    },
    {
      "solution": {
        "revenue": 681660.8509548482
      },
      "time": 160.0
    },
    {
      "solution": {
        "revenue": 681669.7614641031
      },
      "time": 160.0
    },
    {
      "solution": {
        "revenue": 680660.8057276849
      },
      "time": 161.0
    },
    {
      "solution": {
        "revenue": 680803.7239361745
      },
      "time": 161.0
    },
    {
      "solution": {
        "revenue": 680861.6422463318
      },
      "time": 161.0
    },
    {
      "solution": {
        "revenue": 681859.6760760567
      },
      "time": 162.0
    },
    {
      "solution": {
        "revenue": 681880.908916027
      },
      "time": 162.0
    },
    {
      "solution": {
        "revenue": 682041.3285036209
      },
      "time": 163.0
    },
    {
      "solution": {
        "revenue": 682215.1247979045
      },
      "time": 164.0
    },
    {
      "solution": {
        "revenue": 682510.6151784774
      },
      "time": 165.0
    },
    {
      "solution": {
        "revenue": 682540.167324292
      },
      "time": 167.0
    },
    {
      "solution": {
        "revenue": 682705.3526504368
      },
      "time": 168.0
    },
    {
      "solution": {
        "revenue": 681985.4352699072
      },
      "time": 173.0
    },
    {
      "solution": {
        "revenue": 682295.8821702823
      },
      "time": 173.0
    },
    {
      "solution": {
        "revenue": 682297.5892482455
      },
      "time": 174.0
    },
    {
      "solution": {
        "revenue": 654946.657545718
      },
      "time": 175.0
    },
    {
      "solution": {
        "revenue": 655100.7429621682
      },
      "time": 176.0
    },
    {
      "solution": {
        "revenue": 655124.8601802799
      },
      "time": 176.0
    },
    {
      "solution": {
        "revenue": 655531.650329672
      },
      "time": 176.0
    },
    {
      "solution": {
        "revenue": 655725.4474497107
      },
      "time": 176.0
    },
    {
      "solution": {
        "revenue": 657062.023837953
      },
      "time": 177.0
    },
    {
      "solution": {
        "revenue": 658205.0464741943
      },
      "time": 177.0
    },
    {
      "solution": {
        "revenue": 692047.4416354549
      },
      "time": 177.0
    },
    {
      "solution": {
        "revenue": 692136.597502631
      },
      "time": 179.0
    },
    {
      "solution": {
        "revenue": 692229.6506142063
      },
      "time": 180.0
    },
    {
      "solution": {
        "revenue": 692274.2031604811
      },
      "time": 180.0
    },
    {
      "solution": {
        "revenue": 692274.2031604811
      },
      "time": 181.0
    },
    {
      "solution": {
        "revenue": 692662.053462253
      },
      "time": 181.0
    },
    {
      "solution": {
        "revenue": 686963.2164309715
      },
      "time": 183.0
    },
    {
      "solution": {
        "revenue": 686949.4998406821
      },
      "time": 183.0
    },
    {
      "solution": {
        "revenue": 687050.8893288812
      },
      "time": 185.0
    },
    {
      "solution": {
        "revenue": 670157.1502546895
      },
      "time": 187.0
    },
    {
      "solution": {
        "revenue": 670157.1502546895
      },
      "time": 187.0
    },
    {
      "solution": {
        "revenue": 670210.6248366431
      },
      "time": 187.0
    },
    {
      "solution": {
        "revenue": 670529.7599249016
      },
      "time": 188.0
    },
    {
      "solution": {
        "revenue": 670621.3063577944
      },
      "time": 189.0
    },
    {
      "solution": {
        "revenue": 670623.9618124038
      },
      "time": 190.0
    },
    {
      "solution": {
        "revenue": 670739.2631470533
      },
      "time": 192.0
    },
    {
      "solution": {
        "revenue": 670776.8801784387
      },
      "time": 195.0
    },
    {
      "solution": {
        "revenue": 670789.0370539055
      },
      "time": 195.0
    },
    {
      "solution": {
        "revenue": 670796.01528222
      },
      "time": 195.0
    },
    {
      "solution": {
        "revenue": 546014.7588246851
      },
      "time": 196.0
    },
    {
      "solution": {
        "revenue": 581325.2764888856
      },
      "time": 196.0
    },
    {
      "solution": {
        "revenue": 581789.3427150653
      },
      "time": 196.0
    },
    {
      "solution": {
        "revenue": 581933.1598022354
      },
      "time": 197.0
    },
    {
      "solution": {
        "revenue": 582026.1955512229
      },
      "time": 198.0
    },
    {
      "solution": {
        "revenue": 582139.2223503909
      },
      "time": 198.0
    },
    {
      "solution": {
        "revenue": 582387.2315246536
      },
      "time": 199.0
    },
    {
      "solution": {
        "revenue": 582436.8484022188
      },
      "time": 199.0
    },
    {
      "solution": {
        "revenue": 580737.6120549674
      },
      "time": 199.0
    },
    {
      "solution": {
        "revenue": 580128.5622018669
      },
      "time": 203.0
    },
    {
      "solution": {
        "revenue": 582157.5294119319
      },
      "time": 206.0
    },
    {
      "solution": {
        "revenue": 583316.3727214802
      },
      "time": 208.0
    },
    {
      "solution": {
        "revenue": 583473.8974987897
      },
      "time": 208.0
    },
    {
      "solution": {
        "revenue": 583497.1509646329
      },
      "time": 210.0
    },
    {
      "solution": {
        "revenue": 583590.9497920603
      },
      "time": 213.0
    },
    {
      "solution": {
        "revenue": 582088.7206738908
      },
      "time": 214.0
    },
    {
      "solution": {
        "revenue": 580706.8892111352
      },
      "time": 217.0
    },
    {
      "solution": {
        "revenue": 705519.0576042151
      },
      "time": 217.0
    },
    {
      "solution": {
        "revenue": 581002.9140384241
      },
      "time": 217.0
    },
    {
      "solution": {
        "revenue": 581045.3038482334
      },
      "time": 218.0
    },
    {
      "solution": {
        "revenue": 581045.3038482334
      },
      "time": 219.0
    },
    {
      "solution": {
        "revenue": 581234.6521699011
      },
      "time": 220.0
    },
    {
      "solution": {
        "revenue": 581277.0419797102
      },
      "time": 223.0
    },
    {
      "solution": {
        "revenue": 581284.7938645118
      },
      "time": 223.0
    },
    {
      "solution": {
        "revenue": 580221.2875763589
      },
      "time": 223.0
    },
    {
      "solution": {
        "revenue": 580550.5894811203
      },
      "time": 225.0
    },
    {
      "solution": {
        "revenue": 569516.4610026282
      },
      "time": 228.0
    },
    {
      "solution": {
        "revenue": 569746.9894796929
      },
      "time": 230.0
    },
    {
      "solution": {
        "revenue": 569862.3813843122
      },
      "time": 230.0
    },
    {
      "solution": {
        "revenue": 570013.1185570131
      },
      "time": 230.0
    },
    {
      "solution": {
        "revenue": 570027.569628539
      },
      "time": 233.0
    },
    {
      "solution": {
        "revenue": 695476.3728320377
      },
      "time": 235.0
    },
    {
      "solution": {
        "revenue": 695476.3728320377
      },
      "time": 236.0
    },
    {
      "solution": {
        "revenue": 504402.5971307504
      },
      "time": 238.0
    },
    {
      "solution": {
        "revenue": 504585.0268624043
      },
      "time": 238.0
    },
    {
      "solution": {
        "revenue": 504673.3903973685
      },
      "time": 240.0
    },
    {
      "solution": {
        "revenue": 504767.7827991484
      },
      "time": 241.0
    },
    {
      "solution": {
        "revenue": 696071.6880027405
      },
      "time": 243.0
    },
    {
      "solution": {
        "revenue": 696297.0562165694
      },
      "time": 245.0
    },
    {
      "solution": {
        "revenue": 696392.5149584598
      },
      "time": 246.0
    },
    {
      "solution": {
        "revenue": 696492.5129592629
      },
      "time": 247.0
    },
    {
      "solution": {
        "revenue": 696560.1212713261
      },
      "time": 248.0
    },
    {
      "solution": {
        "revenue": 696564.2773131217
      },
      "time": 249.0
    },
    {
      "solution": {
        "revenue": 696630.4594126132
      },
      "time": 251.0
    },
    {
      "solution": {
        "revenue": 696718.2438906829
      },
      "time": 251.0
    },
    {
      "solution": {
        "revenue": 696756.3024643492
      },
      "time": 256.0
    },
    {
      "solution": {
        "revenue": 696815.3936246095
      },
      "time": 257.0
    },
    {
      "solution": {
        "revenue": 473114.97131357936
      },
      "time": 257.0
    },
    {
      "solution": {
        "revenue": 561875.6463461776
      },
      "time": 257.0
    },
    {
      "solution": {
        "revenue": 561875.6463461776
      },
      "time": 257.0
    },
    {
      "solution": {
        "revenue": 685568.9050241011
      },
      "time": 261.0
    },
    {
      "solution": {
        "revenue": 685596.8757153823
      },
      "time": 266.0
    },
    {
      "solution": {
        "revenue": 685629.4962244075
      },
      "time": 266.0
    },
    {
      "solution": {
        "revenue": 685878.1261111851
      },
      "time": 266.0
    },
    {
      "solution": {
        "revenue": 686115.4775746025
      },
      "time": 266.0
    },
    {
      "solution": {
        "revenue": 686115.4775746025
      },
      "time": 268.0
    },
    {
      "solution": {
        "revenue": 686323.5649068975
      },
      "time": 268.0
    },
    {
      "solution": {
        "revenue": 686414.2162181404
      },
      "time": 269.0
    },
    {
      "solution": {
        "revenue": 686408.3815132051
      },
      "time": 270.0
    },
    {
      "solution": {
        "revenue": 686428.853353869
      },
      "time": 273.0
    },
    {
      "solution": {
        "revenue": 696358.3874789439
      },
      "time": 278.0
    },
    {
      "solution": {
        "revenue": 702873.0652652415
      },
      "time": 280.0
    },
    {
      "solution": {
        "revenue": 702769.1392342742
      },
      "time": 280.0
    },
    {
      "solution": {
        "revenue": 702037.0436028314
      },
      "time": 280.0
    },
    {
      "solution": {
        "revenue": 702060.1653172729
      },
      "time": 282.0
    },
    {
      "solution": {
        "revenue": 702101.2336736537
      },
      "time": 283.0
    },
    {
      "solution": {
        "revenue": 702134.7876041548
      },
      "time": 284.0
    },
    {
      "solution": {
        "revenue": 702186.4965641254
      },
      "time": 286.0
    },
    {
      "solution": {
        "revenue": 702216.3621119455
      },
      "time": 286.0
    },
    {
      "solution": {
        "revenue": 702430.7991176947
      },
      "time": 289.0
    },
    {
      "solution": {
        "revenue": 702456.528758485
      },
      "time": 294.0
    },
    {
      "solution": {
        "revenue": 702518.948428965
      },
      "time": 296.0
    },
    {
      "solution": {
        "revenue": 702688.9230571729
      },
      "time": 296.0
    },
    {
      "solution": {
        "revenue": 702042.9805135884
      },
      "time": 297.0
    },
    {
      "solution": {
        "revenue": 702061.8699878183
      },
      "time": 298.0
    }
  ],
  "instance": "5",
  "additionalInformation": {
    "timeLimit": 300,
    "populationSize": 6000,
    "alpha": 0.95,
    "nIter": 10,
    "T0": 0.9999,
    "n": 0,
    "instancePath": "instances/5.json"
  }
}