{
  "bestSolution": {
    "revenue": 1086941
  },
  "checkPoints": [
    {
      "solution": {
        "revenue": 935151
      },
      "time": 0.7269999980926514
    },
    {
      "solution": {
        "revenue": 935389
      },
      "time": 1.071000099182129
    },
    {
      "solution": {
        "revenue": 947363
      },
      "time": 1.124000072479248
    },
    {
      "solution": {
        "revenue": 950389
      },
      "time": 1.255000114440918
    },
    {
      "solution": {
        "revenue": 950545
      },
      "time": 1.6119999885559082
    },
    {
      "solution": {
        "revenue": 953936
      },
      "time": 1.6400001049041748
    },
    {
      "solution": {
        "revenue": 956248
      },
      "time": 1.7249999046325684
    },
    {
      "solution": {
        "revenue": 963210
      },
      "time": 1.8570001125335693
    },
    {
      "solution": {
        "revenue": 967237
      },
      "time": 2.049999952316284
    },
    {
      "solution": {
        "revenue": 996510
      },
      "time": 2.318000078201294
    },
    {
      "solution": {
        "revenue": 1013971
      },
      "time": 2.6429998874664307
    },
    {
      "solution": {
        "revenue": 1021138
      },
      "time": 2.7190001010894775
    },
    {
      "solution": {
        "revenue": 1021333
      },
      "time": 2.885999917984009
    },
    {
      "solution": {
        "revenue": 1023305
      },
      "time": 2.950000047683716
    },
    {
      "solution": {
        "revenue": 1024014
      },
      "time": 3.0850000381469727
    },
    {
      "solution": {
        "revenue": 1029283
      },
      "time": 3.247999906539917
    },
    {
      "solution": {
        "revenue": 1030188
      },
      "time": 3.7300000190734863
    },
    {
      "solution": {
        "revenue": 1030377
      },
      "time": 4.164999961853027
    },
    {
      "solution": {
        "revenue": 1031950
      },
      "time": 4.361000061035156
    },
    {
      "solution": {
        "revenue": 1033579
      },
      "time": 4.38100004196167
    },
    {
      "solution": {
        "revenue": 1034690
      },
      "time": 4.447999954223633
    },
    {
      "solution": {
        "revenue": 1036238
      },
      "time": 4.642999887466431
    },
    {
      "solution": {
        "revenue": 1038474
      },
      "time": 4.953999996185303
    },
    {
      "solution": {
        "revenue": 1038499
      },
      "time": 5.697000026702881
    },
    {
      "solution": {
        "revenue": 1039435
      },
      "time": 5.851999998092651
    },
    {
      "solution": {
        "revenue": 1042749
      },
      "time": 5.890000104904175
    },
    {
      "solution": {
        "revenue": 1050150
      },
      "time": 6.348999977111816
    },
    {
      "solution": {
        "revenue": 1050277
      },
      "time": 7.8399999141693115
    },
    {
      "solution": {
        "revenue": 1051673
      },
      "time": 8.094000101089478
    },
    {
      "solution": {
        "revenue": 1051864
      },
      "time": 8.378000020980835
    },
    {
      "solution": {
        "revenue": 1052644
      },
      "time": 8.553999900817871
    },
    {
      "solution": {
        "revenue": 1053930
      },
      "time": 8.596999883651733
    },
    {
      "solution": {
        "revenue": 1054653
      },
      "time": 8.752000093460083
    },
    {
      "solution": {
        "revenue": 1055397
      },
      "time": 8.9760000705719
    },
    {
      "solution": {
        "revenue": 1055886
      },
      "time": 9.407999992370605
    },
    {
      "solution": {
        "revenue": 1056028
      },
      "time": 9.73200011253357
    },
    {
      "solution": {
        "revenue": 1056029
      },
      "time": 9.992000102996826
    },
    {
      "solution": {
        "revenue": 1056155
      },
      "time": 10.16100001335144
    },
    {
      "solution": {
        "revenue": 1057353
      },
      "time": 10.246000051498413
    },
    {
      "solution": {
        "revenue": 1057830
      },
      "time": 10.315999984741211
    },
    {
      "solution": {
        "revenue": 1057832
      },
      "time": 10.41700005531311
    },
    {
      "solution": {
        "revenue": 1058084
      },
      "time": 10.631999969482422
    },
    {
      "solution": {
        "revenue": 1058279
      },
      "time": 11.128000020980835
    },
    {
      "solution": {
        "revenue": 1059235
      },
      "time": 11.23799991607666
    },
    {
      "solution": {
        "revenue": 1060060
      },
      "time": 12.105000019073486
    },
    {
      "solution": {
        "revenue": 1060158
      },
      "time": 12.233999967575073
    },
    {
      "solution": {
        "revenue": 1060583
      },
      "time": 12.240999937057495
    },
    {
      "solution": {
        "revenue": 1061168
      },
      "time": 13.289999961853027
    },
    {
      "solution": {
        "revenue": 1061577
      },
      "time": 13.528000116348267
    },
    {
      "solution": {
        "revenue": 1061590
      },
      "time": 13.694999933242798
    },
    {
      "solution": {
        "revenue": 1062012
      },
      "time": 13.894000053405762
    },
    {
      "solution": {
        "revenue": 1064114
      },
      "time": 14.102999925613403
    },
    {
      "solution": {
        "revenue": 1065833
      },
      "time": 15.950999975204468
    },
    {
      "solution": {
        "revenue": 1066554
      },
      "time": 16.947999954223633
    },
    {
      "solution": {
        "revenue": 1066687
      },
      "time": 17.003999948501587
    },
    {
      "solution": {
        "revenue": 1066786
      },
      "time": 17.26099991798401
    },
    {
      "solution": {
        "revenue": 1067668
      },
      "time": 17.854000091552734
    },
    {
      "solution": {
        "revenue": 1071310
      },
      "time": 20.381999969482422
    },
    {
      "solution": {
        "revenue": 1072055
      },
      "time": 20.585999965667725
    },
    {
      "solution": {
        "revenue": 1072514
      },
      "time": 20.825000047683716
    },
    {
      "solution": {
        "revenue": 1073382
      },
      "time": 21.878999948501587
    },
    {
      "solution": {
        "revenue": 1073438
      },
      "time": 22.055000066757202
    },
    {
      "solution": {
        "revenue": 1074277
      },
      "time": 28.16000008583069
    },
    {
      "solution": {
        "revenue": 1075205
      },
      "time": 29.21499991416931
    },
    {
      "solution": {
        "revenue": 1075616
      },
      "time": 41.115999937057495
    },
    {
      "solution": {
        "revenue": 1077931
      },
      "time": 41.18899989128113
    },
    {
      "solution": {
        "revenue": 1079133
      },
      "time": 41.40400004386902
    },
    {
      "solution": {
        "revenue": 1079882
      },
      "time": 41.90700006484985
    },
    {
      "solution": {
        "revenue": 1081520
      },
      "time": 42.75699996948242
    },
    {
      "solution": {
        "revenue": 1082440
      },
      "time": 65.21099996566772
    },
    {
      "solution": {
        "revenue": 1082441
      },
      "time": 103.99699997901917
    },
    {
      "solution": {
        "revenue": 1083684
      },
      "time": 128.85400009155273
    },
    {
      "solution": {
        "revenue": 1083736
      },
      "time": 130.4079999923706
    },
    {
      "solution": {
        "revenue": 1083925
      },
      "time": 130.8420000076294
    },
    {
      "solution": {
        "revenue": 1084159
      },
      "time": 131.1119999885559
    },
    {
      "solution": {
        "revenue": 1084163
      },
      "time": 131.97099995613098
    },
    {
      "solution": {
        "revenue": 1084234
      },
      "time": 143.0420000553131
    },
    {
      "solution": {
        "revenue": 1084445
      },
      "time": 144.03800010681152
    },
    {
      "solution": {
        "revenue": 1084677
      },
      "time": 145.0239999294281
    },
    {
      "solution": {
        "revenue": 1084678
      },
      "time": 147.37599992752075
    },
    {
      "solution": {
        "revenue": 1085094
      },
      "time": 157.2260000705719
    },
    {
      "solution": {
        "revenue": 1085095
      },
      "time": 163.82800006866455
    },
    {
      "solution": {
        "revenue": 1085108
      },
      "time": 166.2829999923706
    },
    {
      "solution": {
        "revenue": 1085319
      },
      "time": 180.55399990081787
    },
    {
      "solution": {
        "revenue": 1085972
      },
      "time": 181.10199999809265
    },
    {
      "solution": {
        "revenue": 1086000
      },
      "time": 181.55100011825562
    },
    {
      "solution": {
        "revenue": 1086002
      },
      "time": 181.86700010299683
    },
    {
      "solution": {
        "revenue": 1086269
      },
      "time": 182.51699995994568
    },
    {
      "solution": {
        "revenue": 1086873
      },
      "time": 188.52600002288818
    },
    {
      "solution": {
        "revenue": 1086940
      },
      "time": 283.19799995422363
    },
    {
      "solution": {
        "revenue": 1086941
      },
      "time": 289.7479999065399
    }
  ],
  "instance": "density\u003dHIGH_nInventory\u003d15_nHours\u003d4_seed\u003d5",
  "additionalInformation": {
    "settings": {
      "searchMode": "FIRST_IMPROVEMENT",
      "timeLimit": 300,
      "localSearchSettings": {
        "moves": [
          "insert",
          "outOfPool",
          "interSwap",
          "shift"
        ],
        "neighborhoodSkipProbability": 0.25
      },
      "constructiveHeuristicSettings": {
        "lowerBound": 0.5,
        "upperBound": 2.0
      },
      "alphaGenerator": {
        "lowerBound": 0.1,
        "upperBound": 1.0
      },
      "randomRunN": 0,
      "instancePath": "instances/density\u003dHIGH_nInventory\u003d15_nHours\u003d4_seed\u003d5.json"
    },
    "iterationsPerSecond": 119.95
  }
}