{
  "bestSolution": {
    "revenue": 411775
  },
  "checkPoints": [
    {
      "objective": 362226.0,
      "time": 1.3949999809265137
    },
    {
      "objective": 387652.0,
      "time": 1.4240000247955322
    },
    {
      "objective": 393346.0,
      "time": 1.7760000228881836
    },
    {
      "objective": 394323.0,
      "time": 1.874000072479248
    },
    {
      "objective": 396557.0,
      "time": 1.9760000705718994
    },
    {
      "objective": 400872.0,
      "time": 1.9769999980926514
    },
    {
      "objective": 400900.0,
      "time": 2.2660000324249268
    },
    {
      "objective": 401952.0,
      "time": 2.2669999599456787
    },
    {
      "objective": 402000.0,
      "time": 2.369999885559082
    },
    {
      "objective": 402292.0,
      "time": 2.3889999389648438
    },
    {
      "objective": 402312.0,
      "time": 2.500999927520752
    },
    {
      "objective": 403024.0,
      "time": 2.5460000038146973
    },
    {
      "objective": 403038.0,
      "time": 2.6530001163482666
    },
    {
      "objective": 403153.0,
      "time": 2.86299991607666
    },
    {
      "objective": 403167.0,
      "time": 2.9600000381469727
    },
    {
      "objective": 403384.0,
      "time": 3.0769999027252197
    },
    {
      "objective": 403484.0,
      "time": 3.3940000534057617
    },
    {
      "objective": 403491.0,
      "time": 3.867000102996826
    },
    {
      "objective": 403505.0,
      "time": 4.145999908447266
    },
    {
      "objective": 403508.0,
      "time": 4.147000074386597
    },
    {
      "objective": 403509.0,
      "time": 4.2809998989105225
    },
    {
      "objective": 403830.0,
      "time": 4.2829999923706055
    },
    {
      "objective": 403837.0,
      "time": 4.496999979019165
    },
    {
      "objective": 406091.0,
      "time": 4.997999906539917
    },
    {
      "objective": 406092.0,
      "time": 5.210999965667725
    },
    {
      "objective": 406125.0,
      "time": 5.240999937057495
    },
    {
      "objective": 406261.0,
      "time": 5.2829999923706055
    },
    {
      "objective": 406325.0,
      "time": 5.390000104904175
    },
    {
      "objective": 406336.0,
      "time": 5.414000034332275
    },
    {
      "objective": 406717.0,
      "time": 5.426000118255615
    },
    {
      "objective": 406753.0,
      "time": 5.581000089645386
    },
    {
      "objective": 406755.0,
      "time": 5.599999904632568
    },
    {
      "objective": 406899.0,
      "time": 5.6540000438690186
    },
    {
      "objective": 407524.0,
      "time": 5.789000034332275
    },
    {
      "objective": 408077.0,
      "time": 5.950999975204468
    },
    {
      "objective": 408188.0,
      "time": 6.127000093460083
    },
    {
      "objective": 408242.0,
      "time": 6.227999925613403
    },
    {
      "objective": 408425.0,
      "time": 6.24399995803833
    },
    {
      "objective": 408809.0,
      "time": 6.319999933242798
    },
    {
      "objective": 408822.0,
      "time": 6.5269999504089355
    },
    {
      "objective": 408944.0,
      "time": 6.7179999351501465
    },
    {
      "objective": 408955.0,
      "time": 6.926000118255615
    },
    {
      "objective": 408968.0,
      "time": 6.954999923706055
    },
    {
      "objective": 408969.0,
      "time": 6.959000110626221
    },
    {
      "objective": 408986.0,
      "time": 6.9670000076293945
    },
    {
      "objective": 408991.0,
      "time": 7.005000114440918
    },
    {
      "objective": 409063.0,
      "time": 7.020999908447266
    },
    {
      "objective": 409114.0,
      "time": 7.131999969482422
    },
    {
      "objective": 409115.0,
      "time": 7.1549999713897705
    },
    {
      "objective": 409128.0,
      "time": 7.276000022888184
    },
    {
      "objective": 409160.0,
      "time": 7.322999954223633
    },
    {
      "objective": 409176.0,
      "time": 7.329999923706055
    },
    {
      "objective": 409188.0,
      "time": 7.36299991607666
    },
    {
      "objective": 409196.0,
      "time": 7.392999887466431
    },
    {
      "objective": 409211.0,
      "time": 7.704999923706055
    },
    {
      "objective": 409331.0,
      "time": 7.885999917984009
    },
    {
      "objective": 409346.0,
      "time": 8.141000032424927
    },
    {
      "objective": 409347.0,
      "time": 8.23799991607666
    },
    {
      "objective": 409353.0,
      "time": 8.280999898910522
    },
    {
      "objective": 409354.0,
      "time": 8.397000074386597
    },
    {
      "objective": 409369.0,
      "time": 8.569999933242798
    },
    {
      "objective": 409380.0,
      "time": 8.658999919891357
    },
    {
      "objective": 409896.0,
      "time": 10.155999898910522
    },
    {
      "objective": 410219.0,
      "time": 10.187999963760376
    },
    {
      "objective": 410239.0,
      "time": 10.559999942779541
    },
    {
      "objective": 410245.0,
      "time": 10.677000045776367
    },
    {
      "objective": 410247.0,
      "time": 10.846999883651733
    },
    {
      "objective": 410267.0,
      "time": 10.875
    },
    {
      "objective": 410442.0,
      "time": 11.138999938964844
    },
    {
      "objective": 410443.0,
      "time": 11.239000082015991
    },
    {
      "objective": 410462.0,
      "time": 11.430000066757202
    },
    {
      "objective": 410463.0,
      "time": 11.79200005531311
    },
    {
      "objective": 410466.0,
      "time": 12.056999921798706
    },
    {
      "objective": 410485.0,
      "time": 12.104000091552734
    },
    {
      "objective": 410487.0,
      "time": 12.144999980926514
    },
    {
      "objective": 410664.0,
      "time": 12.164000034332275
    },
    {
      "objective": 410667.0,
      "time": 12.569000005722046
    },
    {
      "objective": 410736.0,
      "time": 12.573999881744385
    },
    {
      "objective": 410741.0,
      "time": 12.696000099182129
    },
    {
      "objective": 410743.0,
      "time": 13.236999988555908
    },
    {
      "objective": 410794.0,
      "time": 13.293999910354614
    },
    {
      "objective": 410798.0,
      "time": 13.678999900817871
    },
    {
      "objective": 410802.0,
      "time": 13.92799997329712
    },
    {
      "objective": 410803.0,
      "time": 13.95799994468689
    },
    {
      "objective": 410815.0,
      "time": 14.663000106811523
    },
    {
      "objective": 410816.0,
      "time": 15.141000032424927
    },
    {
      "objective": 410821.0,
      "time": 16.280999898910522
    },
    {
      "objective": 410823.0,
      "time": 16.674999952316284
    },
    {
      "objective": 410832.0,
      "time": 16.69700002670288
    },
    {
      "objective": 410835.0,
      "time": 17.381999969482422
    },
    {
      "objective": 410845.0,
      "time": 17.42799997329712
    },
    {
      "objective": 410856.0,
      "time": 17.441999912261963
    },
    {
      "objective": 410859.0,
      "time": 17.45900011062622
    },
    {
      "objective": 410860.0,
      "time": 21.47000002861023
    },
    {
      "objective": 410876.0,
      "time": 21.859999895095825
    },
    {
      "objective": 411143.0,
      "time": 25.16599988937378
    },
    {
      "objective": 411199.0,
      "time": 25.58299994468689
    },
    {
      "objective": 411214.0,
      "time": 25.69099998474121
    },
    {
      "objective": 411241.0,
      "time": 26.605000019073486
    },
    {
      "objective": 411246.0,
      "time": 27.763999938964844
    },
    {
      "objective": 411282.0,
      "time": 28.21499991416931
    },
    {
      "objective": 411290.0,
      "time": 28.418999910354614
    },
    {
      "objective": 411291.0,
      "time": 28.52900004386902
    },
    {
      "objective": 411319.0,
      "time": 29.16100001335144
    },
    {
      "objective": 411321.0,
      "time": 29.29699993133545
    },
    {
      "objective": 411337.0,
      "time": 29.72499990463257
    },
    {
      "objective": 411340.0,
      "time": 29.918999910354614
    },
    {
      "objective": 411341.0,
      "time": 30.092999935150146
    },
    {
      "objective": 411342.0,
      "time": 30.766000032424927
    },
    {
      "objective": 411362.0,
      "time": 31.35700011253357
    },
    {
      "objective": 411366.0,
      "time": 36.2279999256134
    },
    {
      "objective": 411370.0,
      "time": 39.21900010108948
    },
    {
      "objective": 411386.0,
      "time": 39.628000020980835
    },
    {
      "objective": 411391.0,
      "time": 39.88199996948242
    },
    {
      "objective": 411392.0,
      "time": 40.7260000705719
    },
    {
      "objective": 411408.0,
      "time": 40.85199999809265
    },
    {
      "objective": 411418.0,
      "time": 40.875
    },
    {
      "objective": 411423.0,
      "time": 40.89100003242493
    },
    {
      "objective": 411427.0,
      "time": 41.12299990653992
    },
    {
      "objective": 411431.0,
      "time": 41.640000104904175
    },
    {
      "objective": 411436.0,
      "time": 41.86299991607666
    },
    {
      "objective": 411474.0,
      "time": 42.355000019073486
    },
    {
      "objective": 411481.0,
      "time": 42.49900007247925
    },
    {
      "objective": 411485.0,
      "time": 43.55999994277954
    },
    {
      "objective": 411546.0,
      "time": 52.27999997138977
    },
    {
      "objective": 411553.0,
      "time": 52.43300008773804
    },
    {
      "objective": 411554.0,
      "time": 52.57200002670288
    },
    {
      "objective": 411565.0,
      "time": 52.65300011634827
    },
    {
      "objective": 411566.0,
      "time": 53.079999923706055
    },
    {
      "objective": 411567.0,
      "time": 53.25
    },
    {
      "objective": 411568.0,
      "time": 53.56599998474121
    },
    {
      "objective": 411569.0,
      "time": 54.85599994659424
    },
    {
      "objective": 411574.0,
      "time": 56.73300004005432
    },
    {
      "objective": 411626.0,
      "time": 58.42899990081787
    },
    {
      "objective": 411664.0,
      "time": 58.526000022888184
    },
    {
      "objective": 411666.0,
      "time": 58.581000089645386
    },
    {
      "objective": 411670.0,
      "time": 58.795000076293945
    },
    {
      "objective": 411672.0,
      "time": 58.806999921798706
    },
    {
      "objective": 411673.0,
      "time": 58.98099994659424
    },
    {
      "objective": 411681.0,
      "time": 59.871999979019165
    },
    {
      "objective": 411682.0,
      "time": 61.07800006866455
    },
    {
      "objective": 411688.0,
      "time": 64.0460000038147
    },
    {
      "objective": 411690.0,
      "time": 66.05599999427795
    },
    {
      "objective": 411691.0,
      "time": 66.6949999332428
    },
    {
      "objective": 411692.0,
      "time": 109.33500003814697
    },
    {
      "objective": 411694.0,
      "time": 112.73900008201599
    },
    {
      "objective": 411725.0,
      "time": 120.68499994277954
    },
    {
      "objective": 411727.0,
      "time": 138.08500003814697
    },
    {
      "objective": 411729.0,
      "time": 138.239000082016
    },
    {
      "objective": 411732.0,
      "time": 144.0880000591278
    },
    {
      "objective": 411754.0,
      "time": 146.20099997520447
    },
    {
      "objective": 411762.0,
      "time": 146.59999990463257
    },
    {
      "objective": 411763.0,
      "time": 146.68600010871887
    },
    {
      "objective": 411764.0,
      "time": 148.22699999809265
    },
    {
      "objective": 411767.0,
      "time": 148.49699997901917
    },
    {
      "objective": 411768.0,
      "time": 183.43300008773804
    },
    {
      "objective": 411771.0,
      "time": 206.93700003623962
    },
    {
      "objective": 411773.0,
      "time": 214.64100003242493
    },
    {
      "objective": 411774.0,
      "time": 232.5880000591278
    },
    {
      "objective": 411775.0,
      "time": 259.03399991989136
    }
  ],
  "instance": "density\u003dLOW_nInventory\u003d12_nHours\u003d3_seed\u003d1",
  "additionalInformation": {
    "settings": {
      "searchMode": "BEST_IMPROVEMENT",
      "timeLimit": 300,
      "localSearchSettings": {
        "moves": [
          "insert",
          "outOfPool",
          "interSwap",
          "shift",
          "transfer",
          "intraSwap"
        ],
        "neighborhoodSkipProbability": 0.5,
        "minProbability": 0.05,
        "updateProbabilitiesAtEveryNIter": 100
      },
      "constructiveHeuristicSettings": {
        "lowerBound": 0.5,
        "upperBound": 2.0
      },
      "alphaGenerator": {
        "alphaValues": [
          0.1,
          0.2,
          0.3,
          0.4,
          0.5,
          0.6,
          0.7,
          0.8,
          0.9
        ],
        "probabilities": [
          0.11050387013978219,
          0.10752416957927399,
          0.11105677532890967,
          0.11207407427137117,
          0.11404700323494235,
          0.10912382847715507,
          0.11243377176453967,
          0.11311061356662551,
          0.11012589363740047
        ],
        "totalQuality": [
          2.302353315E9,
          2.188966792E9,
          2.323393012E9,
          2.362104281E9,
          2.437180132E9,
          2.2498386E9,
          2.375791847E9,
          2.401547703E9,
          2.287970178E9
        ],
        "usageCount": [
          5598,
          5322,
          5649,
          5743,
          5926,
          5470,
          5778,
          5839,
          5563
        ],
        "totalIterations": 50888
      },
      "randomRunN": 1,
      "instancePath": "instances/density\u003dLOW_nInventory\u003d12_nHours\u003d3_seed\u003d1.json"
    },
    "iterationsPerSecond": 169.62666666666667,
    "moveStatistics": {
      "stats": {
        "shift": {
          "attempts": 382726,
          "successes": 359197,
          "totalRevenueGain": 6.2446347E7,
          "totalTimeNanos": 750555113194
        },
        "insert": {
          "attempts": 761683,
          "successes": 130903,
          "totalRevenueGain": 3.59471587E8,
          "totalTimeNanos": 203753394670
        },
        "intraSwap": {
          "attempts": 394268,
          "successes": 378306,
          "totalRevenueGain": 7.0854023E7,
          "totalTimeNanos": 388887008332
        },
        "interSwap": {
          "attempts": 1355687,
          "successes": 1157790,
          "totalRevenueGain": 8.59816159E8,
          "totalTimeNanos": 1712047994274
        },
        "outOfPool": {
          "attempts": 1020691,
          "successes": 682789,
          "totalRevenueGain": 5.86169653E8,
          "totalTimeNanos": 2137441584860
        },
        "transfer": {
          "attempts": 1627376,
          "successes": 1129091,
          "totalRevenueGain": 1.092400389E9,
          "totalTimeNanos": 3502680061636
        }
      }
    },
    "componentEfficacy": {
      "stats": {
        "CONSTRUCTIVE_HEURISTIC": {
          "callCount": 50888,
          "totalTimeNanos": 304445216166,
          "totalRevenueGain": 1.6903420572E10
        },
        "LOCAL_SEARCH": {
          "callCount": 101773,
          "totalTimeNanos": 8697643986217,
          "totalRevenueGain": 3.031158158E9
        },
        "PATH_RELINKING": {
          "callCount": 50885,
          "totalTimeNanos": 273051974057,
          "totalRevenueGain": 9.9456713E8
        }
      }
    }
  }
}