{
  "bestSolution": {
    "revenue": 614617
  },
  "checkPoints": [
    {
      "objective": 599719.0,
      "time": 0.5799999237060547
    },
    {
      "objective": 599747.0,
      "time": 1.2100000381469727
    },
    {
      "objective": 599800.0,
      "time": 1.437999963760376
    },
    {
      "objective": 604203.0,
      "time": 2.8540000915527344
    },
    {
      "objective": 606288.0,
      "time": 3.430999994277954
    },
    {
      "objective": 606368.0,
      "time": 4.0299999713897705
    },
    {
      "objective": 606387.0,
      "time": 4.171999931335449
    },
    {
      "objective": 606525.0,
      "time": 4.4700000286102295
    },
    {
      "objective": 607917.0,
      "time": 4.549999952316284
    },
    {
      "objective": 608550.0,
      "time": 5.1570000648498535
    },
    {
      "objective": 609058.0,
      "time": 6.4649999141693115
    },
    {
      "objective": 609695.0,
      "time": 9.007999897003174
    },
    {
      "objective": 609742.0,
      "time": 9.947999954223633
    },
    {
      "objective": 609826.0,
      "time": 10.611000061035156
    },
    {
      "objective": 609957.0,
      "time": 11.405999898910522
    },
    {
      "objective": 610014.0,
      "time": 12.234999895095825
    },
    {
      "objective": 610336.0,
      "time": 12.424000024795532
    },
    {
      "objective": 610357.0,
      "time": 12.940000057220459
    },
    {
      "objective": 610404.0,
      "time": 13.066999912261963
    },
    {
      "objective": 610515.0,
      "time": 13.58299994468689
    },
    {
      "objective": 610665.0,
      "time": 14.25
    },
    {
      "objective": 610786.0,
      "time": 14.64299988746643
    },
    {
      "objective": 610837.0,
      "time": 16.069000005722046
    },
    {
      "objective": 611611.0,
      "time": 16.28600001335144
    },
    {
      "objective": 611854.0,
      "time": 17.588000059127808
    },
    {
      "objective": 611920.0,
      "time": 17.694999933242798
    },
    {
      "objective": 612246.0,
      "time": 18.328999996185303
    },
    {
      "objective": 612349.0,
      "time": 27.41599988937378
    },
    {
      "objective": 612441.0,
      "time": 31.68400001525879
    },
    {
      "objective": 612462.0,
      "time": 32.15300011634827
    },
    {
      "objective": 612529.0,
      "time": 35.22000002861023
    },
    {
      "objective": 612567.0,
      "time": 36.96399998664856
    },
    {
      "objective": 612636.0,
      "time": 38.50099992752075
    },
    {
      "objective": 612871.0,
      "time": 39.062000036239624
    },
    {
      "objective": 612919.0,
      "time": 43.67899990081787
    },
    {
      "objective": 612923.0,
      "time": 44.144999980926514
    },
    {
      "objective": 612936.0,
      "time": 45.05399990081787
    },
    {
      "objective": 612940.0,
      "time": 48.33699989318848
    },
    {
      "objective": 613055.0,
      "time": 49.92400002479553
    },
    {
      "objective": 613314.0,
      "time": 50.57299995422363
    },
    {
      "objective": 613323.0,
      "time": 51.00200009346008
    },
    {
      "objective": 613366.0,
      "time": 51.456000089645386
    },
    {
      "objective": 613653.0,
      "time": 52.003000020980835
    },
    {
      "objective": 613688.0,
      "time": 52.48699998855591
    },
    {
      "objective": 613748.0,
      "time": 54.551000118255615
    },
    {
      "objective": 613755.0,
      "time": 54.76099991798401
    },
    {
      "objective": 613757.0,
      "time": 56.14299988746643
    },
    {
      "objective": 613758.0,
      "time": 56.88100004196167
    },
    {
      "objective": 613775.0,
      "time": 74.71900010108948
    },
    {
      "objective": 614155.0,
      "time": 79.9670000076294
    },
    {
      "objective": 614173.0,
      "time": 93.20900011062622
    },
    {
      "objective": 614204.0,
      "time": 120.04200005531311
    },
    {
      "objective": 614243.0,
      "time": 128.65199995040894
    },
    {
      "objective": 614325.0,
      "time": 175.05399990081787
    },
    {
      "objective": 614409.0,
      "time": 194.39000010490417
    },
    {
      "objective": 614514.0,
      "time": 221.29900002479553
    },
    {
      "objective": 614531.0,
      "time": 221.56200003623962
    },
    {
      "objective": 614581.0,
      "time": 223.82999992370605
    },
    {
      "objective": 614588.0,
      "time": 224.72199988365173
    },
    {
      "objective": 614617.0,
      "time": 235.83400011062622
    }
  ],
  "instance": "density\u003dHIGH_nInventory\u003d12_nHours\u003d3_seed\u003d7",
  "additionalInformation": {
    "settings": {
      "searchMode": "BEST_IMPROVEMENT",
      "timeLimit": 300,
      "localSearchSettings": {
        "moves": [
          "insert",
          "outOfPool",
          "interSwap",
          "shift",
          "transfer",
          "intraSwap"
        ],
        "neighborhoodSkipProbability": 0.5,
        "minProbability": 0.05,
        "updateProbabilitiesAtEveryNIter": 100
      },
      "constructiveHeuristicSettings": {
        "lowerBound": 0.5,
        "upperBound": 2.0
      },
      "alphaGenerator": {
        "alphaValues": [
          0.1,
          0.2,
          0.3,
          0.4,
          0.5,
          0.6,
          0.7,
          0.8,
          0.9
        ],
        "probabilities": [
          0.10781099937850096,
          0.10140347853091233,
          0.1070562075629124,
          0.11161213960708335,
          0.11473142096642026,
          0.10336041277113484,
          0.12357316376636412,
          0.115527888365738,
          0.11492428905093378
        ],
        "totalQuality": [
          3.65321879E8,
          3.24353001E8,
          3.59340233E8,
          3.88033512E8,
          4.07678759E8,
          3.36064102E8,
          4.63364092E8,
          4.13923547E8,
          4.09505596E8
        ],
        "usageCount": [
          596,
          529,
          586,
          633,
          665,
          548,
          756,
          675,
          668
        ],
        "totalIterations": 5656
      },
      "randomRunN": 2,
      "instancePath": "instances/density\u003dHIGH_nInventory\u003d12_nHours\u003d3_seed\u003d7.json"
    },
    "iterationsPerSecond": 18.85333333333333,
    "moveStatistics": {
      "stats": {
        "outOfPool": {
          "attempts": 224176,
          "successes": 157614,
          "totalRevenueGain": 1.93233833E8,
          "totalTimeNanos": 105274929203
        },
        "intraSwap": {
          "attempts": 50934,
          "successes": 49626,
          "totalRevenueGain": 1.6458341E7,
          "totalTimeNanos": 3544932370
        },
        "insert": {
          "attempts": 38787,
          "successes": 1696,
          "totalRevenueGain": 4212914.0,
          "totalTimeNanos": 13238681503
        },
        "transfer": {
          "attempts": 142494,
          "successes": 84305,
          "totalRevenueGain": 1.10651944E8,
          "totalTimeNanos": 55845558539
        },
        "interSwap": {
          "attempts": 165964,
          "successes": 145764,
          "totalRevenueGain": 1.33302097E8,
          "totalTimeNanos": 45470575623
        },
        "shift": {
          "attempts": 48823,
          "successes": 46619,
          "totalRevenueGain": 1.4261697E7,
          "totalTimeNanos": 7205834061
        }
      }
    },
    "componentEfficacy": {
      "stats": {
        "CONSTRUCTIVE_HEURISTIC": {
          "callCount": 5657,
          "totalTimeNanos": 45623581525,
          "totalRevenueGain": 2.85549579E9
        },
        "LOCAL_SEARCH": {
          "callCount": 11309,
          "totalTimeNanos": 230724692608,
          "totalRevenueGain": 4.72120826E8
        },
        "PATH_RELINKING": {
          "callCount": 5653,
          "totalTimeNanos": 22982821955,
          "totalRevenueGain": 1.40410299E8
        }
      }
    }
  }
}