{
  "bestSolution": {
    "revenue": 1507022
  },
  "checkPoints": [
    {
      "solution": {
        "revenue": 1270201
      },
      "time": 0.6830000877380371
    },
    {
      "solution": {
        "revenue": 1286053
      },
      "time": 0.8810000419616699
    },
    {
      "solution": {
        "revenue": 1344562
      },
      "time": 0.9730000495910645
    },
    {
      "solution": {
        "revenue": 1345380
      },
      "time": 1.5469999313354492
    },
    {
      "solution": {
        "revenue": 1354097
      },
      "time": 1.5810000896453857
    },
    {
      "solution": {
        "revenue": 1357855
      },
      "time": 1.624000072479248
    },
    {
      "solution": {
        "revenue": 1357862
      },
      "time": 1.7960000038146973
    },
    {
      "solution": {
        "revenue": 1361949
      },
      "time": 1.8980000019073486
    },
    {
      "solution": {
        "revenue": 1362085
      },
      "time": 1.9730000495910645
    },
    {
      "solution": {
        "revenue": 1362744
      },
      "time": 2.063999891281128
    },
    {
      "solution": {
        "revenue": 1365815
      },
      "time": 2.078000068664551
    },
    {
      "solution": {
        "revenue": 1368181
      },
      "time": 2.1389999389648438
    },
    {
      "solution": {
        "revenue": 1380027
      },
      "time": 2.193000078201294
    },
    {
      "solution": {
        "revenue": 1380105
      },
      "time": 2.239000082015991
    },
    {
      "solution": {
        "revenue": 1383938
      },
      "time": 2.3329999446868896
    },
    {
      "solution": {
        "revenue": 1385107
      },
      "time": 2.5929999351501465
    },
    {
      "solution": {
        "revenue": 1385514
      },
      "time": 2.697999954223633
    },
    {
      "solution": {
        "revenue": 1386659
      },
      "time": 2.76200008392334
    },
    {
      "solution": {
        "revenue": 1388515
      },
      "time": 2.9200000762939453
    },
    {
      "solution": {
        "revenue": 1389125
      },
      "time": 3.0280001163482666
    },
    {
      "solution": {
        "revenue": 1391158
      },
      "time": 3.065999984741211
    },
    {
      "solution": {
        "revenue": 1392593
      },
      "time": 3.135999917984009
    },
    {
      "solution": {
        "revenue": 1404788
      },
      "time": 3.247999906539917
    },
    {
      "solution": {
        "revenue": 1407251
      },
      "time": 3.312000036239624
    },
    {
      "solution": {
        "revenue": 1408231
      },
      "time": 3.3459999561309814
    },
    {
      "solution": {
        "revenue": 1410921
      },
      "time": 3.390000104904175
    },
    {
      "solution": {
        "revenue": 1412181
      },
      "time": 3.4179999828338623
    },
    {
      "solution": {
        "revenue": 1413634
      },
      "time": 3.4519999027252197
    },
    {
      "solution": {
        "revenue": 1415426
      },
      "time": 3.4679999351501465
    },
    {
      "solution": {
        "revenue": 1423035
      },
      "time": 3.565999984741211
    },
    {
      "solution": {
        "revenue": 1424108
      },
      "time": 3.6540000438690186
    },
    {
      "solution": {
        "revenue": 1425452
      },
      "time": 3.6710000038146973
    },
    {
      "solution": {
        "revenue": 1425510
      },
      "time": 3.8420000076293945
    },
    {
      "solution": {
        "revenue": 1429678
      },
      "time": 3.9660000801086426
    },
    {
      "solution": {
        "revenue": 1429939
      },
      "time": 4.0329999923706055
    },
    {
      "solution": {
        "revenue": 1430957
      },
      "time": 4.135999917984009
    },
    {
      "solution": {
        "revenue": 1432405
      },
      "time": 4.3480000495910645
    },
    {
      "solution": {
        "revenue": 1434531
      },
      "time": 4.539000034332275
    },
    {
      "solution": {
        "revenue": 1436977
      },
      "time": 4.743000030517578
    },
    {
      "solution": {
        "revenue": 1437475
      },
      "time": 5.010999917984009
    },
    {
      "solution": {
        "revenue": 1446819
      },
      "time": 5.019999980926514
    },
    {
      "solution": {
        "revenue": 1447149
      },
      "time": 5.051000118255615
    },
    {
      "solution": {
        "revenue": 1447315
      },
      "time": 5.142999887466431
    },
    {
      "solution": {
        "revenue": 1448283
      },
      "time": 5.171000003814697
    },
    {
      "solution": {
        "revenue": 1448544
      },
      "time": 5.246000051498413
    },
    {
      "solution": {
        "revenue": 1449516
      },
      "time": 5.395999908447266
    },
    {
      "solution": {
        "revenue": 1449739
      },
      "time": 5.45799994468689
    },
    {
      "solution": {
        "revenue": 1452271
      },
      "time": 5.493000030517578
    },
    {
      "solution": {
        "revenue": 1452496
      },
      "time": 5.67300009727478
    },
    {
      "solution": {
        "revenue": 1452895
      },
      "time": 6.197000026702881
    },
    {
      "solution": {
        "revenue": 1454325
      },
      "time": 6.239000082015991
    },
    {
      "solution": {
        "revenue": 1457574
      },
      "time": 6.367000102996826
    },
    {
      "solution": {
        "revenue": 1458280
      },
      "time": 6.783999919891357
    },
    {
      "solution": {
        "revenue": 1460211
      },
      "time": 6.875999927520752
    },
    {
      "solution": {
        "revenue": 1460647
      },
      "time": 6.974999904632568
    },
    {
      "solution": {
        "revenue": 1461888
      },
      "time": 7.059000015258789
    },
    {
      "solution": {
        "revenue": 1463166
      },
      "time": 7.151000022888184
    },
    {
      "solution": {
        "revenue": 1463583
      },
      "time": 7.7190001010894775
    },
    {
      "solution": {
        "revenue": 1466343
      },
      "time": 8.793999910354614
    },
    {
      "solution": {
        "revenue": 1470891
      },
      "time": 8.973999977111816
    },
    {
      "solution": {
        "revenue": 1472506
      },
      "time": 9.651999950408936
    },
    {
      "solution": {
        "revenue": 1472507
      },
      "time": 9.782999992370605
    },
    {
      "solution": {
        "revenue": 1472612
      },
      "time": 10.63100004196167
    },
    {
      "solution": {
        "revenue": 1473259
      },
      "time": 10.707000017166138
    },
    {
      "solution": {
        "revenue": 1474985
      },
      "time": 10.730000019073486
    },
    {
      "solution": {
        "revenue": 1475011
      },
      "time": 11.07200002670288
    },
    {
      "solution": {
        "revenue": 1476732
      },
      "time": 11.226999998092651
    },
    {
      "solution": {
        "revenue": 1477517
      },
      "time": 11.99399995803833
    },
    {
      "solution": {
        "revenue": 1479172
      },
      "time": 12.632999897003174
    },
    {
      "solution": {
        "revenue": 1479386
      },
      "time": 12.655999898910522
    },
    {
      "solution": {
        "revenue": 1479728
      },
      "time": 12.664000034332275
    },
    {
      "solution": {
        "revenue": 1479764
      },
      "time": 13.186000108718872
    },
    {
      "solution": {
        "revenue": 1479909
      },
      "time": 13.20199990272522
    },
    {
      "solution": {
        "revenue": 1480502
      },
      "time": 13.288000106811523
    },
    {
      "solution": {
        "revenue": 1481703
      },
      "time": 13.842000007629395
    },
    {
      "solution": {
        "revenue": 1482410
      },
      "time": 14.015000104904175
    },
    {
      "solution": {
        "revenue": 1482755
      },
      "time": 14.065000057220459
    },
    {
      "solution": {
        "revenue": 1482896
      },
      "time": 16.808000087738037
    },
    {
      "solution": {
        "revenue": 1483028
      },
      "time": 16.92799997329712
    },
    {
      "solution": {
        "revenue": 1483373
      },
      "time": 17.372999906539917
    },
    {
      "solution": {
        "revenue": 1486720
      },
      "time": 17.996999979019165
    },
    {
      "solution": {
        "revenue": 1487155
      },
      "time": 18.013000011444092
    },
    {
      "solution": {
        "revenue": 1487743
      },
      "time": 18.186000108718872
    },
    {
      "solution": {
        "revenue": 1488984
      },
      "time": 18.293999910354614
    },
    {
      "solution": {
        "revenue": 1489626
      },
      "time": 18.430999994277954
    },
    {
      "solution": {
        "revenue": 1489692
      },
      "time": 18.611999988555908
    },
    {
      "solution": {
        "revenue": 1490038
      },
      "time": 18.64199995994568
    },
    {
      "solution": {
        "revenue": 1490439
      },
      "time": 19.00600004196167
    },
    {
      "solution": {
        "revenue": 1491037
      },
      "time": 19.02300000190735
    },
    {
      "solution": {
        "revenue": 1491382
      },
      "time": 19.933000087738037
    },
    {
      "solution": {
        "revenue": 1491383
      },
      "time": 19.94099998474121
    },
    {
      "solution": {
        "revenue": 1492642
      },
      "time": 20.32100009918213
    },
    {
      "solution": {
        "revenue": 1492643
      },
      "time": 20.691999912261963
    },
    {
      "solution": {
        "revenue": 1493171
      },
      "time": 21.183000087738037
    },
    {
      "solution": {
        "revenue": 1493772
      },
      "time": 21.40000009536743
    },
    {
      "solution": {
        "revenue": 1493977
      },
      "time": 23.789999961853027
    },
    {
      "solution": {
        "revenue": 1494028
      },
      "time": 23.880000114440918
    },
    {
      "solution": {
        "revenue": 1494569
      },
      "time": 24.747999906539917
    },
    {
      "solution": {
        "revenue": 1494841
      },
      "time": 24.884000062942505
    },
    {
      "solution": {
        "revenue": 1495115
      },
      "time": 25.430999994277954
    },
    {
      "solution": {
        "revenue": 1495775
      },
      "time": 25.47099995613098
    },
    {
      "solution": {
        "revenue": 1496201
      },
      "time": 25.937000036239624
    },
    {
      "solution": {
        "revenue": 1497958
      },
      "time": 30.71399998664856
    },
    {
      "solution": {
        "revenue": 1498214
      },
      "time": 31.382999897003174
    },
    {
      "solution": {
        "revenue": 1498360
      },
      "time": 34.12400007247925
    },
    {
      "solution": {
        "revenue": 1498482
      },
      "time": 38.09599995613098
    },
    {
      "solution": {
        "revenue": 1498622
      },
      "time": 43.23200011253357
    },
    {
      "solution": {
        "revenue": 1498878
      },
      "time": 49.75399994850159
    },
    {
      "solution": {
        "revenue": 1498889
      },
      "time": 52.48799991607666
    },
    {
      "solution": {
        "revenue": 1499403
      },
      "time": 54.25500011444092
    },
    {
      "solution": {
        "revenue": 1500238
      },
      "time": 61.7960000038147
    },
    {
      "solution": {
        "revenue": 1500945
      },
      "time": 62.24499988555908
    },
    {
      "solution": {
        "revenue": 1501880
      },
      "time": 62.71199989318848
    },
    {
      "solution": {
        "revenue": 1502284
      },
      "time": 64.94099998474121
    },
    {
      "solution": {
        "revenue": 1502963
      },
      "time": 69.59100008010864
    },
    {
      "solution": {
        "revenue": 1503082
      },
      "time": 77.98300004005432
    },
    {
      "solution": {
        "revenue": 1503171
      },
      "time": 78.1029999256134
    },
    {
      "solution": {
        "revenue": 1503282
      },
      "time": 78.77999997138977
    },
    {
      "solution": {
        "revenue": 1503912
      },
      "time": 84.84299993515015
    },
    {
      "solution": {
        "revenue": 1504577
      },
      "time": 99.20000004768372
    },
    {
      "solution": {
        "revenue": 1504869
      },
      "time": 101.2039999961853
    },
    {
      "solution": {
        "revenue": 1505090
      },
      "time": 103.66599988937378
    },
    {
      "solution": {
        "revenue": 1505137
      },
      "time": 106.39499998092651
    },
    {
      "solution": {
        "revenue": 1505934
      },
      "time": 110.32599997520447
    },
    {
      "solution": {
        "revenue": 1505935
      },
      "time": 115.74600005149841
    },
    {
      "solution": {
        "revenue": 1506384
      },
      "time": 122.39100003242493
    },
    {
      "solution": {
        "revenue": 1506387
      },
      "time": 159.74699997901917
    },
    {
      "solution": {
        "revenue": 1506506
      },
      "time": 210.6470000743866
    },
    {
      "solution": {
        "revenue": 1506509
      },
      "time": 239.20099997520447
    },
    {
      "solution": {
        "revenue": 1506711
      },
      "time": 242.30800008773804
    },
    {
      "solution": {
        "revenue": 1506763
      },
      "time": 262.5380001068115
    },
    {
      "solution": {
        "revenue": 1506866
      },
      "time": 264.51900005340576
    },
    {
      "solution": {
        "revenue": 1507022
      },
      "time": 289.9389998912811
    }
  ],
  "instance": "density\u003dHIGH_nInventory\u003d20_nHours\u003d5_seed\u003d10",
  "additionalInformation": {
    "settings": {
      "searchMode": "BEST_IMPROVEMENT",
      "timeLimit": 300,
      "localSearchSettings": {
        "moves": [
          "insert",
          "outOfPool",
          "interSwap",
          "shift"
        ],
        "neighborhoodSkipProbability": 0.5
      },
      "constructiveHeuristicSettings": {
        "lowerBound": 0.5,
        "upperBound": 2.0
      },
      "alphaGenerator": {
        "alpha": 0.25
      },
      "randomRunN": 0,
      "instancePath": "instances/density\u003dHIGH_nInventory\u003d20_nHours\u003d5_seed\u003d10.json"
    },
    "iterationsPerSecond": 120.75
  }
}