{
  "bestSolution": {
    "revenue": 1032414
  },
  "checkPoints": [
    {
      "solution": {
        "revenue": 907200
      },
      "time": 1.2699999809265137
    },
    {
      "solution": {
        "revenue": 943154
      },
      "time": 1.3369998931884766
    },
    {
      "solution": {
        "revenue": 945793
      },
      "time": 1.6540000438690186
    },
    {
      "solution": {
        "revenue": 950170
      },
      "time": 1.8440001010894775
    },
    {
      "solution": {
        "revenue": 957238
      },
      "time": 1.9909999370574951
    },
    {
      "solution": {
        "revenue": 959184
      },
      "time": 2.006999969482422
    },
    {
      "solution": {
        "revenue": 960839
      },
      "time": 2.0290000438690186
    },
    {
      "solution": {
        "revenue": 961341
      },
      "time": 2.0290000438690186
    },
    {
      "solution": {
        "revenue": 965729
      },
      "time": 2.0299999713897705
    },
    {
      "solution": {
        "revenue": 967329
      },
      "time": 2.0390000343322754
    },
    {
      "solution": {
        "revenue": 967685
      },
      "time": 2.0450000762939453
    },
    {
      "solution": {
        "revenue": 969620
      },
      "time": 2.0480000972747803
    },
    {
      "solution": {
        "revenue": 970158
      },
      "time": 2.072999954223633
    },
    {
      "solution": {
        "revenue": 979447
      },
      "time": 2.0739998817443848
    },
    {
      "solution": {
        "revenue": 980855
      },
      "time": 2.1040000915527344
    },
    {
      "solution": {
        "revenue": 983174
      },
      "time": 2.118000030517578
    },
    {
      "solution": {
        "revenue": 983382
      },
      "time": 2.119999885559082
    },
    {
      "solution": {
        "revenue": 984220
      },
      "time": 2.122999906539917
    },
    {
      "solution": {
        "revenue": 984394
      },
      "time": 2.128999948501587
    },
    {
      "solution": {
        "revenue": 985330
      },
      "time": 2.1429998874664307
    },
    {
      "solution": {
        "revenue": 985695
      },
      "time": 2.1489999294281006
    },
    {
      "solution": {
        "revenue": 988327
      },
      "time": 2.1610000133514404
    },
    {
      "solution": {
        "revenue": 989191
      },
      "time": 2.250999927520752
    },
    {
      "solution": {
        "revenue": 989891
      },
      "time": 2.2909998893737793
    },
    {
      "solution": {
        "revenue": 994035
      },
      "time": 2.3519999980926514
    },
    {
      "solution": {
        "revenue": 994923
      },
      "time": 2.3550000190734863
    },
    {
      "solution": {
        "revenue": 995706
      },
      "time": 2.4570000171661377
    },
    {
      "solution": {
        "revenue": 995715
      },
      "time": 2.4730000495910645
    },
    {
      "solution": {
        "revenue": 998307
      },
      "time": 2.4800000190734863
    },
    {
      "solution": {
        "revenue": 1001136
      },
      "time": 2.5409998893737793
    },
    {
      "solution": {
        "revenue": 1002597
      },
      "time": 2.5490000247955322
    },
    {
      "solution": {
        "revenue": 1002896
      },
      "time": 2.562999963760376
    },
    {
      "solution": {
        "revenue": 1002898
      },
      "time": 2.569999933242798
    },
    {
      "solution": {
        "revenue": 1002899
      },
      "time": 2.572000026702881
    },
    {
      "solution": {
        "revenue": 1003809
      },
      "time": 2.5759999752044678
    },
    {
      "solution": {
        "revenue": 1004204
      },
      "time": 2.609999895095825
    },
    {
      "solution": {
        "revenue": 1004206
      },
      "time": 2.63100004196167
    },
    {
      "solution": {
        "revenue": 1004679
      },
      "time": 2.6689999103546143
    },
    {
      "solution": {
        "revenue": 1007256
      },
      "time": 2.7019999027252197
    },
    {
      "solution": {
        "revenue": 1008035
      },
      "time": 2.7309999465942383
    },
    {
      "solution": {
        "revenue": 1008718
      },
      "time": 2.8580000400543213
    },
    {
      "solution": {
        "revenue": 1009084
      },
      "time": 2.872999906539917
    },
    {
      "solution": {
        "revenue": 1009086
      },
      "time": 2.885999917984009
    },
    {
      "solution": {
        "revenue": 1011367
      },
      "time": 2.8989999294281006
    },
    {
      "solution": {
        "revenue": 1011530
      },
      "time": 2.9660000801086426
    },
    {
      "solution": {
        "revenue": 1012606
      },
      "time": 2.9690001010894775
    },
    {
      "solution": {
        "revenue": 1013264
      },
      "time": 3.006999969482422
    },
    {
      "solution": {
        "revenue": 1013291
      },
      "time": 3.2100000381469727
    },
    {
      "solution": {
        "revenue": 1013531
      },
      "time": 3.2260000705718994
    },
    {
      "solution": {
        "revenue": 1014284
      },
      "time": 3.303999900817871
    },
    {
      "solution": {
        "revenue": 1014952
      },
      "time": 3.3310000896453857
    },
    {
      "solution": {
        "revenue": 1015042
      },
      "time": 3.3399999141693115
    },
    {
      "solution": {
        "revenue": 1015083
      },
      "time": 3.369999885559082
    },
    {
      "solution": {
        "revenue": 1015215
      },
      "time": 3.380000114440918
    },
    {
      "solution": {
        "revenue": 1015437
      },
      "time": 3.38700008392334
    },
    {
      "solution": {
        "revenue": 1015817
      },
      "time": 3.4820001125335693
    },
    {
      "solution": {
        "revenue": 1016148
      },
      "time": 3.5920000076293945
    },
    {
      "solution": {
        "revenue": 1016306
      },
      "time": 3.759999990463257
    },
    {
      "solution": {
        "revenue": 1016867
      },
      "time": 3.890000104904175
    },
    {
      "solution": {
        "revenue": 1017591
      },
      "time": 4.007999897003174
    },
    {
      "solution": {
        "revenue": 1018190
      },
      "time": 4.084000110626221
    },
    {
      "solution": {
        "revenue": 1018192
      },
      "time": 4.0940001010894775
    },
    {
      "solution": {
        "revenue": 1018915
      },
      "time": 4.104000091552734
    },
    {
      "solution": {
        "revenue": 1019494
      },
      "time": 4.17300009727478
    },
    {
      "solution": {
        "revenue": 1019544
      },
      "time": 4.184999942779541
    },
    {
      "solution": {
        "revenue": 1020092
      },
      "time": 4.186000108718872
    },
    {
      "solution": {
        "revenue": 1020242
      },
      "time": 4.2190001010894775
    },
    {
      "solution": {
        "revenue": 1020277
      },
      "time": 4.240999937057495
    },
    {
      "solution": {
        "revenue": 1020933
      },
      "time": 4.2820000648498535
    },
    {
      "solution": {
        "revenue": 1021015
      },
      "time": 4.546999931335449
    },
    {
      "solution": {
        "revenue": 1021203
      },
      "time": 4.6519999504089355
    },
    {
      "solution": {
        "revenue": 1023164
      },
      "time": 5.499000072479248
    },
    {
      "solution": {
        "revenue": 1024137
      },
      "time": 5.533999919891357
    },
    {
      "solution": {
        "revenue": 1024278
      },
      "time": 5.578000068664551
    },
    {
      "solution": {
        "revenue": 1024381
      },
      "time": 5.696000099182129
    },
    {
      "solution": {
        "revenue": 1024696
      },
      "time": 5.716000080108643
    },
    {
      "solution": {
        "revenue": 1024699
      },
      "time": 5.813999891281128
    },
    {
      "solution": {
        "revenue": 1024780
      },
      "time": 5.8399999141693115
    },
    {
      "solution": {
        "revenue": 1024782
      },
      "time": 5.8459999561309814
    },
    {
      "solution": {
        "revenue": 1024962
      },
      "time": 5.943000078201294
    },
    {
      "solution": {
        "revenue": 1025001
      },
      "time": 6.1570000648498535
    },
    {
      "solution": {
        "revenue": 1025046
      },
      "time": 6.246999979019165
    },
    {
      "solution": {
        "revenue": 1025527
      },
      "time": 6.4059998989105225
    },
    {
      "solution": {
        "revenue": 1025735
      },
      "time": 6.730000019073486
    },
    {
      "solution": {
        "revenue": 1026752
      },
      "time": 6.765000104904175
    },
    {
      "solution": {
        "revenue": 1026768
      },
      "time": 6.786999940872192
    },
    {
      "solution": {
        "revenue": 1026831
      },
      "time": 6.812999963760376
    },
    {
      "solution": {
        "revenue": 1026850
      },
      "time": 6.822000026702881
    },
    {
      "solution": {
        "revenue": 1026851
      },
      "time": 6.8450000286102295
    },
    {
      "solution": {
        "revenue": 1026852
      },
      "time": 6.924000024795532
    },
    {
      "solution": {
        "revenue": 1027000
      },
      "time": 7.841000080108643
    },
    {
      "solution": {
        "revenue": 1027001
      },
      "time": 7.911999940872192
    },
    {
      "solution": {
        "revenue": 1027002
      },
      "time": 8.844000101089478
    },
    {
      "solution": {
        "revenue": 1027324
      },
      "time": 9.099999904632568
    },
    {
      "solution": {
        "revenue": 1027398
      },
      "time": 10.015000104904175
    },
    {
      "solution": {
        "revenue": 1028059
      },
      "time": 15.678999900817871
    },
    {
      "solution": {
        "revenue": 1028116
      },
      "time": 15.943000078201294
    },
    {
      "solution": {
        "revenue": 1028402
      },
      "time": 16.77900004386902
    },
    {
      "solution": {
        "revenue": 1028522
      },
      "time": 17.26799988746643
    },
    {
      "solution": {
        "revenue": 1028663
      },
      "time": 18.52900004386902
    },
    {
      "solution": {
        "revenue": 1028825
      },
      "time": 18.57699990272522
    },
    {
      "solution": {
        "revenue": 1028826
      },
      "time": 26.60800004005432
    },
    {
      "solution": {
        "revenue": 1029375
      },
      "time": 30.924999952316284
    },
    {
      "solution": {
        "revenue": 1029411
      },
      "time": 34.0789999961853
    },
    {
      "solution": {
        "revenue": 1029464
      },
      "time": 37.78200006484985
    },
    {
      "solution": {
        "revenue": 1030016
      },
      "time": 41.609999895095825
    },
    {
      "solution": {
        "revenue": 1030387
      },
      "time": 46.62599992752075
    },
    {
      "solution": {
        "revenue": 1030388
      },
      "time": 46.62899994850159
    },
    {
      "solution": {
        "revenue": 1030448
      },
      "time": 48.681999921798706
    },
    {
      "solution": {
        "revenue": 1030449
      },
      "time": 49.26799988746643
    },
    {
      "solution": {
        "revenue": 1030466
      },
      "time": 49.79900002479553
    },
    {
      "solution": {
        "revenue": 1030537
      },
      "time": 49.80299997329712
    },
    {
      "solution": {
        "revenue": 1030621
      },
      "time": 49.8050000667572
    },
    {
      "solution": {
        "revenue": 1030622
      },
      "time": 50.04900002479553
    },
    {
      "solution": {
        "revenue": 1031656
      },
      "time": 51.12700009346008
    },
    {
      "solution": {
        "revenue": 1031657
      },
      "time": 51.15700006484985
    },
    {
      "solution": {
        "revenue": 1031824
      },
      "time": 51.76699995994568
    },
    {
      "solution": {
        "revenue": 1031829
      },
      "time": 51.769999980926514
    },
    {
      "solution": {
        "revenue": 1032414
      },
      "time": 52.31100010871887
    }
  ],
  "instance": "density\u003dHIGH_nInventory\u003d15_nHours\u003d4_seed\u003d7",
  "additionalInformation": {
    "settings": {
      "searchMode": "FIRST_IMPROVEMENT",
      "timeLimit": 300,
      "localSearchSettings": {
        "moves": [
          "insert",
          "outOfPool",
          "interSwap",
          "shift",
          "transfer",
          "intraSwap"
        ],
        "neighborhoodSkipProbability": 0.5
      },
      "constructiveHeuristicSettings": {
        "lowerBound": 0.5,
        "upperBound": 2.0
      },
      "alphaGenerator": {
        "lowerBound": 0.1,
        "upperBound": 1.0
      },
      "randomRunN": 0,
      "instancePath": "instances/density\u003dHIGH_nInventory\u003d15_nHours\u003d4_seed\u003d7.json"
    },
    "iterationsPerSecond": 2741.7466666666664
  }
}